Workbook

Sheet Evaluación_ideas
B2: EVALUACIÓN DE IDEAS DE NEGOCIO
B3: FORMATO DE DESCRIPCIÓN DE IDEAS DE NEGOCIO
B4: No | C4: Nombre de la Idea del Negocio | D4: Fuente de Identificación de la Idea del Negocio | E4: Breve descripción de la Idea del Negocio | F4: Principal Razon Por la que Puede Ser Una Idea Ganadora
B5: 1 | C5: Turismo Senior | D5: Tendencia demográfica y notas de prensa sobre el auge de viajes 60+; escasez de paquetes accesibles | E5: Agencia que diseña y opera viajes “slow” con logística médica, guías formados y destinos fuera de temporada | F5: Mercado en rápido crecimiento y capacidad de desestacionalizar la oferta turística, generando ingresos todo el año
B6: 2 | C6: Asistente Virtual para la Tercera Edad | D6: Reportes sobre soledad no deseada y adopción de interfaces de voz | E6: Altavoz/app IA que recuerda medicación, conecta con voluntarios y monitorea bienestar | F6: Alta necesidad social, barreras de salida altas una vez el usuario adopta la plataforma (stickiness)
B7: 3 | C7: Centro de Acondicionamiento Senior | D7: Datos OMS/Ministerio sobre sedentarismo > 50 % en mayores | E7: Gimnasio boutique con programas gerontológicos, monitoreo médico y convenios EPS | F7: Convierte un problema de salud pública en ingresos recurrentes; posibilidad de cofinanciación por aseguradoras
B8: 4 | C8: ActivaVida – Dispositivo de Equilibrio y Reflejos | D8: Estadísticas de caídas (1 de 3 mayores/año) y papers de propiocepción | E8: Ecosistema de dispositivos modulares (disco IMU, banda, pads) + app y analítica para fisios | F8: Hardware low‑cost + servicio SaaS: alto impacto clínico, ingresos por venta y suscripción
B9: 5 | C9: Snacks Nutricionales Senior | D9: Estudios sobre anorexia de la edad y sarcopenia | E9: Línea de bocados blandos, ricos en proteína y fibra, bajos en azúcar y sal | F9: Nicho poco atendido; sinergia con farmacias/geriátricos y tendencia “healthy aging”
B10: 6 | C10: Huertos Intergeneracionales | D10: Programas municipales de huertas y evidencias de integración social | E10: Instalación y mentoría de huertas urbanas que reúnen jóvenes y mayores | F10: Alto impacto social y bajo costo operativo; elegible a subvenciones públicas
B11: 7 | C11: AbueloAmigo | D11: Iniciativas como “Voces en Red” y redes de voluntariado locales | E11: Plataforma que empareja seniors con voluntarios para llamadas y salidas | F11: Escalable digitalmente y con costes de infraestructura mínimos
B12: 8 | C12: SeniorGames | D12: Meta‑análisis de exergames que mejoran equilibrio y cognición | E12: Consola/app de juegos adaptativos con sensores de movimiento y niveles ajustables | F12: Combina entretenimiento y salud, mercado global de “seniors games” al alza
B13: 9 | C13: Puertas Inteligentes Seguras | D13: Estadísticas de caídas y accidentes domésticos en adultos mayores; artículos sobre automatización del hogar y estudios que muestran aceptación de monitoreo por parte de seniors | E13: Cerraduras y sensores inteligentes que impiden quedar encerrado, alertan caídas en el marco de la puerta y permiten apertura remota por familiares o cuidadores | F13: Resuelve un dolor crítico (seguridad en el hogar) con tecnología ya madura y con alta disposición de pago; se integra fácilmente a ecosistemas de smart‑home y genera ingresos recurrentes por monitoreo y mantenimiento
B14: 10
B15: 11
B16: 12
B17: 13
B18: 14

Sheet Valoración-ideas
B2: EVALUACION DE IDEAS DE NEGOCIO
B3: FORMATO DE EVALUACION DE IDEAS DE NEGOCIO
B4: No | C4: Idea de Negocio | D4: Perspectiva Personal | I4: Perspectiva de Mercado | Q4: Perspectiva de Recursos | W4: Perspectiva Legal
C5: CRITERIOS DE EVALUACIÓN 5 - Totalmente 4 - En un alto porcentaje 3 - En un porcentaje aceptable 2 - Muy poco 1 - Nada | D5: Vibro con la idea me gusta mucho | E5: Tengo el talento para sacar la idea adelante | F5: Tengo conocimiento en este campo | G5: Poseo experiencia practica | H5: Tengo red de contactos | I5: El producto sería valorado por el mercado final | J5: Tiene potencial en el mercado | K5: Estabilidad del mercado en ciclos económicos | L5: Incremento proyectado del número de consumidores (población consumidora en aumento) | M5: La idea busca atender necesidades insatisfechas | N5: Conozco la competencia | O5: Sé Como podría llegar al mercado objetivo | P5: La idea tiene elementos innovadores, diferenciadores | Q5: Tiene capacidad de conseguir un equipo con el perfil requerido | R5: Tengo acceso a la tecnología requerida | S5: Puedo conseguir los insumos y materia prima requerida | T5: asegurado el suministro de materias primas, (disponibilidad estable, bajos costos) | U5: cuento con los recursos económicos y/o posibles fuentes de financiación | V5: El negocio Puede ser rentable | W5: Aspectos legales | X5: Patentes, licencias | Y5: Legislación controles ambientales | Z5: TOTAL | AC5: ,
B6: 1 | C6: Turismo Senior | D6: =(3+4+5+4)/4 -> 4 | E6: =(2+3+2+2)/4 -> 2.25 | F6: =(2+1+2+1)/4 -> 1.5 | G6: =(2+1+1+1)/4 -> 1.25 | H6: =(2+2+3+3)/4 -> 2.5 | I6: =(3+3+4+3)/4 -> 3.25 | J6: =(3+4+5+3)/4 -> 3.75 | K6: =(3+4+4+4)/4 -> 3.75 | L6: =(4+5+5+5)/4 -> 4.75 | M6: =(4+5+4+5)/4 -> 4.5 | N6: =(2+1+2+1)/4 -> 1.5 | O6: =(2+5+4+2)/4 -> 3.25 | P6: =(2+3+3+3)/4 -> 2.75 | Q6: =(4+4+4+4)/4 -> 4 | R6: =(4+1+4+1)/4 -> 2.5 | S6: =(4+4+4+4)/4 -> 4 | T6: =(3+3+3+4)/4 -> 3.25 | U6: =(1+1+1+1)/4 -> 1 | V6: =(3+4+4+3)/4 -> 3.5 | W6: =(4+3+2+3)/4 -> 3 | X6: =(3+3+3+3)/4 -> 3 | Y6: =(4+5+5+4)/4 -> 4.5 | Z6: =AVERAGE(D6:Y6) -> 3.0795455
B7: 2 | C7: Asistente Virtual para la Tercera Edad | D7: =(3+4+5+4)/4 -> 4 | E7: =(5+3+2+4)/4 -> 3.5 | F7: =(4+1+2+3)/4 -> 2.5 | G7: =(4+1+1+3)/4 -> 2.25 | H7: =(2+2+3+3)/4 -> 2.5 | I7: =(3+3+4+3)/4 -> 3.25 | J7: =(3+4+5+4)/4 -> 4 | K7: =(3+4+4+4)/4 -> 3.75 | L7: =(4+5+5+5)/4 -> 4.75 | M7: =(4+5+4+5)/4 -> 4.5 | N7: =(2+1+2+1)/4 -> 1.5 | O7: =(2+5+4+3)/4 -> 3.5 | P7: =(2+3+3+3)/4 -> 2.75 | Q7: =(4+4+4+4)/4 -> 4 | R7: =(4+1+4+4)/4 -> 3.25 | S7: =(4+4+4+4)/4 -> 4 | T7: =(4+3+3+4)/4 -> 3.5 | U7: =(4+1+1+1)/4 -> 1.75 | V7: =(2+4+4+3)/4 -> 3.25 | W7: =(4+3+2+4)/4 -> 3.25 | X7: =(4+3+3+3)/4 -> 3.25 | Y7: =(4+5+5+4)/4 -> 4.5 | Z7: =AVERAGE(D7:Y7) -> 3.3409091
B8: 3 | C8: Centro de Acondicionamiento Senior | D8: =(3+4+5+5)/4 -> 4.25 | E8: =(2+3+2+3)/4 -> 2.5 | F8: =(2+2+2+3)/4 -> 2.25 | G8: =(2+3+1+3)/4 -> 2.25 | H8: =(2+1+3+2)/4 -> 2 | I8: =(3+4+4+4)/4 -> 3.75 | J8: =(3+1+5+4)/4 -> 3.25 | K8: =(3+2+4+4)/4 -> 3.25 | L8: =(4+5+5+5)/4 -> 4.75 | M8: =(3+5+4+5)/4 -> 4.25 | N8: =(3+1+2+1)/4 -> 1.75 | O8: =(2+5+4+3)/4 -> 3.5 | P8: =(2+1+3+3)/4 -> 2.25 | Q8: =(2+1+4+4)/4 -> 2.75 | R8: =(2+1+4+4)/4 -> 2.75 | S8: =(3+1+4+4)/4 -> 3 | T8: =(3+1+3+4)/4 -> 2.75 | U8: =(1+1+1+1)/4 -> 1 | V8: =(3+1+4+3)/4 -> 2.75 | W8: =(4+1+2+3)/4 -> 2.5 | X8: =(3+3+3+3)/4 -> 3 | Y8: =(4+5+5+4)/4 -> 4.5 | Z8: =AVERAGE(D8:Y8) -> 2.9545455
B9: 4 | C9: ActivaVida – Dispositivo de Equilibrio y Reflejos | D9: =(5+3+5+4)/4 -> 4.25 | E9: =(5+2+3+2)/4 -> 3 | F9: =(4+1+2+2)/4 -> 2.25 | G9: =(4+1+1+1)/4 -> 1.75 | H9: =(3+1+3+3)/4 -> 2.5 | I9: =(4+3+5+3)/4 -> 3.75 | J9: =(4+2+5+4)/4 -> 3.75 | K9: =(4+2+5+4)/4 -> 3.75 | L9: =(5+5+5+5)/4 -> 5 | M9: =(4+3+5+5)/4 -> 4.25 | N9: =(3+1+2+1)/4 -> 1.75 | O9: =(4+4+4+2)/4 -> 3.5 | P9: =(5+2+4+4)/4 -> 3.75 | Q9: =(4+1+4+4)/4 -> 3.25 | R9: =(4+1+4+3)/4 -> 3 | S9: =(4+2+4+4)/4 -> 3.5 | T9: =(3+3+4+4)/4 -> 3.5 | U9: =(4+1+4+1)/4 -> 2.5 | V9: =(4+3+4+3)/4 -> 3.5 | W9: =(4+3+2+3)/4 -> 3 | X9: =(4+4+2+3)/4 -> 3.25 | Y9: =(4+5+5+4)/4 -> 4.5 | Z9: =AVERAGE(D9:Y9) -> 3.3295455
B10: 5 | C10: Snacks Nutricionales Senior | D10: =(2+4+1+4)/4 -> 2.75 | E10: =(2+3+1+2)/4 -> 2 | F10: =(1+2+1+3)/4 -> 1.75 | G10: =(1+1+1+2)/4 -> 1.25 | H10: =(2+1+3+2)/4 -> 2 | I10: =(3+3+4+3)/4 -> 3.25 | J10: =(2+4+2+3)/4 -> 2.75 | K10: =(3+4+2+4)/4 -> 3.25 | L10: =(4+5+5+5)/4 -> 4.75 | M10: =(2+5+4+5)/4 -> 4 | N10: =(2+1+1+2)/4 -> 1.5 | O10: =(1+5+2+2)/4 -> 2.5 | P10: =(2+3+2+3)/4 -> 2.5 | Q10: =(2+4+4+4)/4 -> 3.5 | R10: =(2+1+4+2)/4 -> 2.25 | S10: =(4+4+4+4)/4 -> 4 | T10: =(3+3+2+4)/4 -> 3 | U10: =(1+1+1+1)/4 -> 1 | V10: =(3+4+2+3)/4 -> 3 | W10: =(2+3+1+3)/4 -> 2.25 | X10: =(3+3+2+3)/4 -> 2.75 | Y10: =(3+5+2+4)/4 -> 3.5 | Z10: =AVERAGE(D10:Y10) -> 2.7045455
B11: 6 | C11: Huertos Intergeneracionales | D11: =(2+4+2+4)/4 -> 3 | E11: =(1+3+2+2)/4 -> 2 | F11: =(1+1+2+1)/4 -> 1.25 | G11: =(1+1+1+1)/4 -> 1 | H11: =(2+2+1+3)/4 -> 2 | I11: =(3+3+4+3)/4 -> 3.25 | J11: =(3+4+2+3)/4 -> 3 | K11: =(2+4+2+4)/4 -> 3 | L11: =(4+5+5+5)/4 -> 4.75 | M11: =(2+5+2+5)/4 -> 3.5 | N11: =(2+1+2+1)/4 -> 1.5 | O11: =(2+5+4+2)/4 -> 3.25 | P11: =(2+3+2+3)/4 -> 2.5 | Q11: =(2+4+4+4)/4 -> 3.5 | R11: =(4+1+5+1)/4 -> 2.75 | S11: =(4+4+5+4)/4 -> 4.25 | T11: =(2+3+5+4)/4 -> 3.5 | U11: =(1+1+4+1)/4 -> 1.75 | V11: =(3+4+2+3)/4 -> 3 | W11: =(3+3+4+3)/4 -> 3.25 | X11: =(3+3+5+3)/4 -> 3.5 | Y11: =(4+5+5+4)/4 -> 4.5 | Z11: =AVERAGE(D11:Y11) -> 2.9090909
B12: 7 | C12: AbueloAmigo | D12: =(2+4+5+4)/4 -> 3.75 | E12: =(2+3+4+3)/4 -> 3 | F12: =(2+1+4+3)/4 -> 2.5 | G12: =(1+1+1+3)/4 -> 1.5 | H12: =(2+2+2+2)/4 -> 2 | I12: =(3+3+4+3)/4 -> 3.25 | J12: =(3+4+4+3)/4 -> 3.5 | K12: =(3+4+4+4)/4 -> 3.75 | L12: =(4+5+5+5)/4 -> 4.75 | M12: =(4+5+4+5)/4 -> 4.5 | N12: =(2+1+1+1)/4 -> 1.25 | O12: =(2+5+2+2)/4 -> 2.75 | P12: =(2+3+2+3)/4 -> 2.5 | Q12: =(4+4+4+4)/4 -> 4 | R12: =(4+1+4+1)/4 -> 2.5 | S12: =(4+4+4+4)/4 -> 4 | T12: =(2+3+4+4)/4 -> 3.25 | U12: =(1+1+1+1)/4 -> 1 | V12: =(2+4+4+3)/4 -> 3.25 | W12: =(4+3+4+3)/4 -> 3.5 | X12: =(3+3+5+3)/4 -> 3.5 | Y12: =(4+5+5+4)/4 -> 4.5 | Z12: =AVERAGE(D12:Y12) -> 3.1136364
B13: 8 | C13: SeniorGames | D13: =(4+4+5+4)/4 -> 4.25 | E13: =(4+4+4+3)/4 -> 3.75 | F13: =(2+2+3+3)/4 -> 2.5 | G13: =(1+1+1+2)/4 -> 1.25 | H13: =(2+3+4+2)/4 -> 2.75 | I13: =(3+5+4+4)/4 -> 4 | J13: =(3+5+5+4)/4 -> 4.25 | K13: =(3+3+5+4)/4 -> 3.75 | L13: =(4+5+5+5)/4 -> 4.75 | M13: =(4+5+5+5)/4 -> 4.75 | N13: =(2+3+1+1)/4 -> 1.75 | O13: =(2+5+4+3)/4 -> 3.5 | P13: =(2+5+5+4)/4 -> 4 | Q13: =(4+4+5+4)/4 -> 4.25 | R13: =(4+2+5+3)/4 -> 3.5 | S13: =(4+4+4+4)/4 -> 4 | T13: =(3+3+5+4)/4 -> 3.75 | U13: =(1+1+1+1)/4 -> 1 | V13: =(3+5+5+3)/4 -> 4 | W13: =(4+3+5+3)/4 -> 3.75 | X13: =(3+3+4+3)/4 -> 3.25 | Y13: =(4+5+5+4)/4 -> 4.5 | Z13: =AVERAGE(D13:Y13) -> 3.5113636
B14: 9
B15: 10
B16: 11
B17: 12
B18: 13
B19: 14
B20: 15
C21: EJEMPLOS
C22: Servicio de correo para tiendas y pequeños negocios | D22: 5 | E22: 5 | F22: 4 | G22: 4 | H22: 5 | I22: 4 | J22: 4 | K22: 5 | L22: 3 | M22: 4 | N22: 3 | O22: 2 | P22: 3 | Q22: 4 | R22: 3 | S22: 5 | T22: 4 | U22: 4 | V22: 4 | W22: 5 | X22: 4 | Y22: 5 | Z22: =AVERAGE(D22:Y22) -> 4.0454545
C23: Producción y venta de bocadillo dietético | D23: 3 | E23: 3 | F23: 2 | G23: 2 | H23: 4 | I23: 5 | J23: 4 | K23: 5 | L23: 5 | M23: 3 | N23: 2 | O23: 2 | P23: 4 | Q23: 5 | R23: 4 | S23: 5 | T23: 5 | U23: 4 | V23: 3 | W23: 5 | X23: 3 | Y23: 4 | Z23: =AVERAGE(D23:Y23) -> 3.7272727
B24: * Para obtener el total, se suman todos los puntajes de la idea y se dividen por 22 (total de factores que se califican)

Sheet IdeavsEstrategia
B2: Proyecto Vs Estrategia Organizacional
B3: Objetivo: | C3: Identificar la relación existente entre la Idea de Proyecto y la Estrategia Organizacional
B4: Componentes | D4: Preguntas | E4: Detalles
B5: PERSPECTIVA (POR QUE) | C5: Antecedentes de negocio | D5: Por que debemos hacer el proyecto? | E5: Quien es el cliente/Usuario
D6: Cual es la perspectiva de negocio y la motivación? | E6: Cual es su necesidad?
E7: Como lograremos satisfacer esa necesidad?
E8: Cual es la oportunidad de negocio?
C9: Objetivo de negocio | D9: Que queremos conseguir como negocio? | E9: Cual es la meta de negocio que se conseguirá una vez el resultado del proyecto sea generado?
C10: Concepto estratégico | D10: Por que el proyecto soportara la estrategia de negocios de la compañía? | E10: Cual es el principio de solución estratégico que guiara el plan y la ejecución del proyecto y soportara la estrategia de la compañía?
D11: Cual es la idea competitiva estratégica?
B12: POSICION (QUE) | C12: Definición de producto | D12: Cual es el producto que será creado o producido por el proyecto? | E12: Que vamos a producir?
E13: Que tipo de producto es?
E14: Cual es su concepto de operación y sus principales características?
C15: Ventaja Competitiva/Valor | D15: Que tan bueno es? | E15: Cual es la ventaja para el cliente/usuario sobre:
D16: Por que es mejor que sus competidores? | E16: Competidores ?
D17: Por que es mejor que el proceso/estado actual? | E17: Productos previos?
D18: Por que el cliente lo compraría? | E18: Soluciones Alternativas?
D19: Cual es el valor para nosotros? | E19: Costo/Efectividad del producto, como podría beneficiarnos?
C20: Criterios de éxito/falla | D20: Cuales son las expectativas? | E20: Cuales son las dimensiones del éxito y sus indicadores?
D21: Como mediremos el éxito del proyecto?
D22: Que puede ir mal? | E22: Cuales son los principales riesgos y sus consecuencias?
B24: Proyecto Vs Estrategia Organizacional
B25: Objetivo: | C25: Identificar la relación existente entre la Idea de Proyecto y la Estrategia Organizacional
B26: Componentes | D26: Preguntas | E26: Detalles
B27: PERSPECTIVA (POR QUE) | C27: Antecedentes de negocio | D27: Altas tasas de caídas en adultos mayores (1 de cada 3 al año), aumento del sedentarismo y deterioro cognitivo. Costos sanitarios por caídas cercanos al 1% del PIB en Colombia. | E27: Adultos mayores (60+), cuidadores/familias, clínicas y fisioterapeutas, EPS y aseguradoras.
D28: El envejecimiento poblacional (20% de mayores en 2040) exige soluciones accesibles de prevención y monitoreo en el hogar. | E28: Prevenir caídas y deterioro cognitivo con herramientas motivadoras y accesibles, con datos clínicos confiables para la toma de decisiones médicas.
E29: Mediante un ecosistema de dispositivos lúdicos + app móvil + portal de analítica clínica con seguimiento remoto.
E30: Mercado TAM en Colombia de alrededor de 500 M (USD); crecimiento anual de 13% en tele-rehabilitación en LatAm; escasez de competidores que integren hardware low-cost, gamificación y datos clínicos.
C31: Objetivo de negocio | D31: Meta de 10.000 usuarios activos y 50 clínicas aliadas en 24 meses; reducir en 15% las caídas y mejorar en 20% el tiempo de reacción en usuarios. | E31: Cual es la meta de negocio que se conseguirá una vez el resultado del proyecto sea generado?
C32: Concepto estratégico | D32: Refuerza la visión de ser plataforma líder en salud activa y preventiva para adultos mayores, integrando IoT y analítica clínica accesible. | E32: Modelo Device-as-a-Service (kits en arriendo o venta + suscripción digital).
D33: Hardware modular low-cost, gamificación social y reportes clínicos automatizados que mejoran adherencia y diferencian frente a apps solo-software o equipos clínicos premium. | K33: 0 | L33: 5 | M33: 4 | N33: 5 | O33: =SUM(E33:N33)/10 -> 1.4
B34: POSICION (QUE) | C34: Definición de producto | D34: Ecosistema compuesto por: banda IMU, disco de equilibrio, pads táctiles, app móvil (React Native), backend analítico y portal clínico. | E34: Kits físicos + plataforma digital + servicio de suscripción y analítica.
E35: Solución integrada de hardware + software + servicio (salud digital).
E36: Plug-and-play, retos lúdicos guiados, feedback visual/háptico, conectividad cloud, reportes clínicos automáticos.
C37: Ventaja Competitiva/Valor | D37: Ofrece prevención medible, divertida y accesible. | E37: Cual es la ventaja para el cliente/usuario sobre:
D38: Competidores: apps solo-software (sin métricas físicas); plataformas clínicas premium (muy costosas, solo para hospitales). ActivaVida ofrece bajo costo + usabilidad en el hogar. | E38: Competidores ?
D39: Estado actual: fisioterapia presencial limitada, sin datos objetivos en casa. La solución permite prevención diaria, adherencia y evidencia clínica. | E39: Productos previos?
D40: Porque reduce riesgo de caídas y deterioro cognitivo, mejora la autonomía, genera confianza familiar y datos útiles para médicos/EPS. | E40: Soluciones Alternativas?
D41: Márgenes 40% en hardware, ingresos recurrentes por suscripción SaaS, expansión de portafolio B2B con analítica para aseguradoras. | E41: Costo/Efectividad del producto, como podría beneficiarnos?
C42: Criterios de éxito/falla | D42: Impacto clínico: reducción 15% caídas y mejora 20% reflejos. Negocio: ARR > USD 2M al año 2. Uso: 8.000 MAU al mes 18. | E42: Cuales son las dimensiones del éxito y sus indicadores?
D43: Estudios pre/post clínicos, KPIs de uso (adherencia 30 días > 60%), dashboards financieros y de analítica.
D44: Riesgos: retrasos en certificación Invima, baja adopción tecnológica en seniors, fallas de hardware, fugas de datos. Consecuencias: entrada tardía, pérdida de confianza o multas regulatorias. | E44: Cuales son los principales riesgos y sus consecuencias?

Sheet Arbol Problemas
B2: ÁRBOL DEL PROBLEMAS
B4: Efectos Indirectos | D4: Disminución de la esperanza de vida saludable | F4: Aumento de la carga familiar y "cuidadores" | H4: Reducción de participación en actividades comunitarias | L4: Mayor dependencia de servicios asistenciales | AF4: ÁRBOL DE PROBLEMAS
B6: Efectos Indirectos | D6: Estrés económico en familias | F6: Aumento de depresión | H6: Pérdida de autonomía personal | L6: Sobrecarga de EPS y clínicas | AF6: Efectos Indirectos | AH6: Disminución de participación en el mercado | AJ6: Pérdida de competitividad frente a rivales | AL6: Reducción de ingresos y rentabilidad
R7: 🔽 Causas (raíces):
B8: Efectos Indirectos | D8: Mayor riesgo de aislamiento social | F8: Deterioro de la autoestima | H8: Deterioro cognitivo acelerado | L8: Reducción del bienestar general | R8: 1 | S8: Falta de planeación urbana para el crecimiento vehicular | AF8: Efectos Indirectos | AH8: Clientes migran hacia la competencia | AJ8: Disminución de confianza de inversionistas | AL8: Pérdida de posicionamiento en el sector
R9: 2 | S9: Ausencia de políticas de control de parqueo en vía pública
B10: Efectos Directos | C10: . | D10: Aumento de costos sanitarios | H10: Fracturas y lesiones graves | J10: Periodos de recuperación más largos | L10: Reducción de movilidad y equilibrio | R10: 3 | S10: Poca inversión en infraestructura de parqueaderos públicos | AF10: Efectos Indirectos | AH10: Desaprovechamiento de tendencias tecnológicas | AJ10: Reputación debilitada ante stakeholders | AL10: Menor capacidad de innovación
R11: 4 | S11: Alta densidad vehicular en zonas comerciales y residenciales
B12: Problema Central | D12: Falta de herramientas y procesos efectivos para la prevención de caídas en adultos mayores, con baja continuidad y escaso seguimiento de datos clínicos. | R12: 5 | S12: Débil regulación de construcciones sin áreas de estacionamiento | AF12: Efectos Directos | AG12: . | AH12: Estrategias de marketing poco alineadas con el mercado | AJ12: Pérdida de oportunidades comerciales | AL12: Baja efectividad de campañas publicitarias
R13: 🔼 Efectos (consecuencias):
B14: Causas Directas | D14: Ineficacia en tratamientos médicos | F14: Falta de monitoreo remoto | H14: Ausencia de programas lúdicos | L14: Escaso acceso a tecnología adaptada a necesidades particulares | R14: 1 | S14: Mayor congestión vehicular en zonas críticas | AF14: Problema Central | AH14: La empresa carece de procesos efectivos para identificar y aprovechar oportunamente las oportunidades y tendencias de mercado, lo que limita la eficacia de sus estrategias de marketing.
R15: 2 | S15: Reducción de la movilidad urbana y aumento del tiempo de desplazamiento
B16: Causas Indirectas | D16: Demora para diágnosticos de enfermedades degenerativas y resultados | H16: Diagnóstico tardío | J16: Escasez de profesionales especializados | L16: Diagnósticos tardíos de enfermedades degenerativas | R16: 3 | S16: Invasión del espacio público por vehículos mal estacionados | AF16: Causas Directas | AH16: Falta de sistemas de análisis de datos en tiempo real | AJ16: Procesos de toma de decisiones lentos y burocráticos | AL16: Escasa cultura de innovación
R17: 4 | S17: Disminución de la calidad de vida de los residentes
B18: Causas Indirectas | D18: Demora entre citas | H18: Demoras en asignación de citas | J18: Protocolos de prevención desactualizados | L18: Falta de innovación tecnológica accesible | R18: 5 | S18: Pérdidas económicas para comercios locales por dificultad de acceso | AF18: Causas Indirectas | AH18: Dependencia de estudios de mercado tradicionales y desactualizados | AJ18: Limitada inversión en herramientas tecnológicas | AL18: Escasez de personal especializado en análisis de tendencias
B20: Causas Indirectas | D20: Hay falta de profesionales en el sector salud | H20: Desigualdad en cobertura de programas de prevención | J20: Baja cultura de envejecimiento activo y hábitos de ejercicio en mayores | L20: Escasa industria de dispositivos de salud en el país | AF20: Causas Indirectas | AH20: Falta de integración de fuentes de datos internas y externas | AJ20: Ausencia de metodologías ágiles en gestión estratégica | AL20: Escasa colaboración interdepartamental
B22: Causas Indirectas | D22: Saturación en el sector salud | H22: Falta de incentivos a innovación para prevención | J22: Escaso apoyo a desarrollo de talento en geriatría y fisioterapia | L22: Poca articulación entre gobierno, EPS y sector privado | AF22: Causas Indirectas | AH22: Poca inversión en I+D aplicada al marketing | AJ22: Desconexión con universidades o centros de innovación | AL22: Falta de incentivos para la innovación organizacional

Sheet Marco logico
B2: METODOLOGÍA MARCO LÓGICO
B7: 1. IDENTIFICAR EL PROBLEMA
B9: Existe una falta de herramientas y procesos efectivos para prevenir caídas y deterioro cognitivo en adultos mayores. Esta situación genera baja continuidad en los tratamientos, escaso seguimiento de datos clínicos, y un incremento en la dependencia, costos de atención y deterioro de la calidad de vida.
B18: 2. ANALIZAR GRUPOS DE INTERES O INVOLUCRADOS DEL PROYECTO
B19: https://ingenioempresa.com/analisis-involucrados-marco-logico/
B21: a. Elaboración de la tabla de participación (identificar los interesados)
B22: b. Definir los roles y su participacion
B24: a. Indentificacion de interesados Diagnostico de la población afectada y del entorno en general | C24: b. Roles y su participacion | N24: Ejemplo de categorizacion de los interesados
B25: Grupos | C25: Roles de los actores | D25: Tipo de participacion | E25: Intereses | F25: Problemáticas | H25: Recursos/ Mandatos
B26: 1. Org. Del sector publico | C26: Cooperante/Beneficiario | D26: Informar/asesorar | E26: Reducir carga al sistema de salud; promover envejecimiento activo | F26: Saturación en el sistema de salud; falta de innovación preventiva | H26: Políticas públicas, financiación estatal, normativas de salud | N26: Roles de los actores | O26: Tipo de participacion
B27: 2. Org. Del sector privado | C27: Beneficiario | D27: Informar | E27: Acceso a nuevos mercados, reputación social, inversión en salud preventiva | F27: Falta de acceso a datos clínicos para desarrollar soluciones | H27: Inversión, tecnología, canales de distribución | N27: Cooperante | O27: Informar
B28: 3. Org. Del sector sociedad civil | C28: Cooperante | D28: Aliado | E28: Mejorar calidad de vida de mayores; participación comunitaria | F28: Baja cultura de envejecimiento activo; aislamiento social | H28: Programas sociales, redes comunitarias | N28: Beneficiario | O28: Asesorar
B29: 4. Org. Religiosas | C29: Afectados | D29: consultar | E29: Bienestar integral de sus adultos mayores; red de apoyo espiritual\ | F29: Escasa inclusión de sus miembros en estrategias de salud | H29: Voluntariado, espacios comunitarios | N29: Afectados | O29: Aliado
B30: 5. Org. Externas | C30: opositor | D30: control | E30: Verificar impactos sociales, éticos y regulatorios | F30: Preocupaciones por privacidad, sostenibilidad y equidad en acceso tecnológico | H30: Organismos internacionales, ONGs, reguladores externos | N30: opositor | O30: consultar
B33: c. Agruparlos y priorizarlos
B35: Criterio | C35: Calificacion grupo
B36: ALTO | C36: 3
B37: MEDIO | C37: 2
B38: BAJO | C38: 1
B41: d. Analizar grupos de interes
B43: Criterio de Selección | C43: Peso del criterio | D43: Grupo 1 | F43: Grupo 2 | H43: Grupo 3 | J43: Grupo 4 | L43: Grupo 5
D44: Calificacion | E44: Resultado | F44: Calificacion | G44: Resultado | H44: Calificacion | I44: Resultado | J44: Calificacion | K44: Resultado | L44: Calificacion | M44: Resultado
B45: PODER | C45: 0.5 | D45: 3 | E45: =+D45*C45 -> 1.5 | F45: 3 | G45: =+C45*F45 -> 1.5 | H45: 3 | I45: =C45*H45 -> 1.5 | J45: 1 | K45: =$C$45*J45 -> 0.5 | L45: 2 | M45: =$C$45*L45 -> 1
B46: INTERES | C46: 0.3 | D46: 2 | E46: =+D46*C46 -> 0.6 | F46: 2 | G46: =+C46*F46 -> 0.6 | H46: 1 | I46: =C46*H46 -> 0.3 | J46: 2 | K46: =$C$45*J46 -> 1 | L46: 1 | M46: =$C$45*L46 -> 0.5
B47: INFLUENCIA | C47: 0.2 | D47: 3 | E47: =+D47*C47 -> 0.6 | F47: 3 | G47: =+C47*F47 -> 0.6 | H47: 1 | I47: =+C47*H47 -> 0.2 | J47: 1 | K47: =$C$45*J47 -> 0.5 | L47: 1 | M47: =$C$45*L47 -> 0.5
B48: Totales | C48: =SUM(C45:C47) -> 1 | D48: Subtotal Grupo 1 | E48: =SUM(E45:E47) -> 2.7 | F48: Subtotal Grupo 2 | G48: =SUM(G45:G47) -> 2.7 | H48: Subtotal Grupo 3 | I48: =SUM(I45:I47) -> 2 | J48: Subtotal Grupo 3 | K48: =SUM(K45:K47) -> 2 | L48: Subtotal Grupo 3 | M48: =SUM(M45:M47) -> 2
B51: e. Matriz -Valorando los involucrados (Poder e interes) Agrupa a los interesados basándose en su nivel de autoridad para controlar las decisiones de un proyecto, facilitar su ejecución o dificultarla –económica-política-social etc. (“poder”) y su nivel de preocupación (“interés”) con respecto a los resultados del proyecto. | F51: e. Matriz -Valorando los involucrados (Influencia e Impacto) Agrupa a los interesados basándose en su participación activa (“influencia”) en el proyecto y su capacidad de efectuar cambios a la planificación o ejecución del proyecto (“impacto”).
F55: INFLUENCIA | G55: ALTA
J56: Org. del sector privado; Org. del sector público
H60: Org. religiosas; Org. externas / ONGs / reguladores | J60: Org. sociedad civil
G61: BAJA
H65: BAJA | J65: ALTA
H66: IMPACTO
B69: e. Establecer estrategias con el involucrado
B71: Grupos | C71: Estrategia
B72: 1. Org. Del sector publico | C72: Involucramiento activo y sostenido. Facilitar toma de decisiones y coordinación interinstitucional.
B73: 2. Org. Del sector privado | C73: Establecer alianzas estratégicas. Incentivar su participación como co-ejecutores y promotores del proyecto.
B74: 3. Org. Del sector sociedad civil | C74: Fomentar participación ciudadana mediante espacios de diálogo y consulta. Promover mecanismos de veeduría social.
B75: 4. Org. Religiosas | C75: Mantener informadas. Consultas puntuales sobre impacto comunitario.
B76: 5. Org. Externas | C76: Mitigar oposición mediante negociación y transparencia. Escuchar recomendaciones técnicas y asegurar cumplimiento normativo.
B79: 3. ARBOL DE PROBLEMAS
B80: https://ingenioempresa.com/arbol-de-problemas/
B85: 4. ARBOL DE OBJETIVOS
B86: https://ingenioempresa.com/arbol-de-objetivos/
B93: 5. ANALISIS DE ALTERNATIVAS Y SELECCIÓN DE LA ESTRATEGIA
B94: https://ingenioempresa.com/analisis-de-alternativas/
B96: criterio | C96: calificacion
B97: ALTO | C97: 3
B98: MEDIO | C98: 2
B99: BAJO | C99: 1
B103: Criterio de selección | C103: Peso del criterio | D103: Asistente Virtual para la Tercera Edad | F103: ActivaVida – Dispositivo de Equilibrio y Reflejos | H103: AbueloAmigo
D104: Calificacion | E104: Resultado | F104: Calificacion | G104: Resultado | H104: Calificacion | I104: Resultado
B105: Beneficio | C105: 0.25 | D105: 3 | E105: =D105*$C$105 -> 0.75 | F105: 2 | G105: =F105*C105 -> 0.5 | H105: 2 | I105: =H105*C105 -> 0.5
B106: Tiempo | C106: 0.1 | D106: 2 | E106: =D106*C106 -> 0.2 | F106: 3 | G106: =F106*C106 -> 0.3 | H106: 2 | I106: =H106*C106 -> 0.2
B107: Costo | C107: 0.1 | D107: 2 | E107: =D107*C107 -> 0.2 | F107: 3 | G107: =F107*C107 -> 0.3 | H107: 3 | I107: =H107*C107 -> 0.3
B108: Impacto Ambiental | C108: 0.1 | D108: 2 | E108: =D108*C108 -> 0.2 | F108: 3 | G108: =F108*C108 -> 0.3 | H108: 3 | I108: =H108*C108 -> 0.3
B109: Riesgo Social | C109: 0.15 | D109: 2 | E109: =D109*C109 -> 0.3 | F109: 2 | G109: =F109*C109 -> 0.3 | H109: 3 | I109: =H109*C109 -> 0.45
B110: Viabilidad | C110: 0.2 | D110: 2 | E110: =D110*C110 -> 0.4 | F110: 3 | G110: =F110*C110 -> 0.6 | H110: 2 | I110: =H110*C110 -> 0.4
B111: Riesgo Financiero | C111: 0.1 | D111: 2 | E111: =D111*C111 -> 0.2 | F111: 3 | G111: =F111*C111 -> 0.3 | H111: 2 | I111: =H111*C111 -> 0.2
B112: Totales | C112: suma 100% | D112: sumatoria | E112: =SUM(E105:E111) -> 2.25 | F112: sumatoria | G112: =SUM(G105:G111) -> 2.6 | H112: sumatoria | I112: =SUM(I105:I111) -> 2.35
B115: 6. CONSTRUCCION DE LA MATRIZ
B116: https://ingenioempresa.com/resumen-narrativo/
B118: Lógica: Horizontal: Vertical: | C118: Logica Intervencion | D118: Indicadores objetivamente verificables | E118: Fuentes de Verificacionn | F118: Hipótesis/Supuestos (Factores externos)
B120: https://ingenioempresa.com/resumen-narrativo/#Fin_finalidad_del_proyecto | D120: https://ingenioempresa.com/indicadores-marco-logico/ | E120: https://ingenioempresa.com/medios-de-verificacion/ | F120: https://ingenioempresa.com/supuestos-marco-logico/
B121: FIN (fin del árbol de objetivos) ¿Por qué el proyecto es importante para los beneficiarios y la sociedad? | C121: Fin general Contribuir a reducir la incidencia de caídas y deterioro cognitivo en adultos mayores, mejorando su autonomía y calidad de vida. | D121: Fin medible - Reducción del 15% en la tasa de caídas en población 60+ en 2 años. - Mejora del 20% en pruebas de tiempo de reacción y memoria funcional en usuarios activos en 2 años. - Aumento del 10% en percepción de bienestar reportada por usuarios/cuidadores. | E121: Fuente para verificar el cumplimiento del FIN - Reportes del Ministerio de Salud y EPS. - Estudios clínicos de seguimiento. - Encuestas de calidad de vida a usuarios y cuidadores. - Datos agregados de la plataforma. | F121: Factores externos que mantienen la estrategia, la Sustentabilidad y las Suposiciones - Apoyo de entidades de salud y políticas públicas en envejecimiento activo. - Estabilidad en sistemas de salud (EPS/IPS). - Aceptación cultural y familiar del uso de soluciones tecnológicas en adultos mayores.
B122: PROPÓSITO (G: solución focal E: medios directos seleccionados en la estrategia) ¿Por qué el proyecto es necesario para los beneficiarios? | C122: General: propósito Específicos. Ofrecer un sistema integral, accesible y motivador que combine dispositivos lúdicos + app + analítica clínica para prevenir caídas y deterioro cognitivo en adultos mayores. | D122: Objetivos medibles - ≥ 10.000 usuarios activos en 24 meses. - ≥ 50 clínicas/fisioterapeutas aliados en 2 años. - ≥ 60% de adherencia a sesiones mensuales en usuarios activos. - Retención de usuarios (30 días) ≥ 60%. | E122: Fuente para verificar el cumplimiento del objetivo - Bases de datos de la plataforma (MAU, retención, sesiones). - Contratos y registros de alianzas con clínicas/EPS. - Estudios pre-post clínicos en usuarios (equilibrio, cognición). | F122: Factores externos que mantienen la estrategia, la Sustentabilidad y las Suposiciones - Adultos mayores y cuidadores cuentan con acceso a smartphones e internet. - Profesionales de salud muestran disposición a usar datos digitales en su práctica. - Regulación sanitaria (INVIMA) permite comercialización sin retrasos críticos.
B123: Resultados (PRODUCTOS) (medios indirectos 1er Seleccionados en la estrategia) ¿Qué entregará el proyecto? | C123: Bienes y servicios. kits de dispositivos (banda IMU, disco de equilibrio, pads táctiles), app móvil, backend analítico y portal clínico. | D123: Resultados medibles - Desarrollo y validación de MVP funcional en 2026. - ≥ 3 módulos de hardware certificados e integrados con app. - Plataforma SaaS clínica operativa con dashboards multiusuario. - Campañas de educación y capacitación realizadas en ≥ 5 municipios. | E123: Fuentes verificables para corroborar que si se hizo el producto INTERNAS PROYECTO - Reportes de I+D y validaciones técnicas. - Certificación sanitaria (INVIMA, ISO 13485 light). - Registro de capacitaciones y talleres. - Reportes de usuarios piloto y feedback clínico. | F123: Factores externos que mantienen la estrategia, la Sustentabilidad y las Suposiciones - Proveedores de hardware cumplen con estándares de calidad. - Disponibilidad de fondos para I+D y certificaciones. - Participación activa de adultos mayores y clínicas en pilotos.
B124: Actividades (medios indirectos 2do Seleccionados en la estrategia) ¿Qué se hará? | C124: Acción para transformar los INSUMOS en los resultados según los planificado. - Diseñar, prototipar y validar dispositivos de bajo costo. - Desarrollar app (React Native) y backend analítico. - Ejecutar pruebas piloto con usuarios y clínicas. - Gestionar certificación sanitaria e integración con EPS. - Implementar campañas educativas y programa “Embajadores Senior”. | D124: Insumos requeridos Presupuesto - Recursos invertidos en I+D (USD, % del presupuesto). - Número de prototipos desarrollados y probados. - Número de pilotos implementados (n≥50 usuarios, ≥2 clínicas). - Número de campañas educativas realizadas. | E124: Costos No siempre en $$$ Fuentes para verificar el desempeño - Reportes financieros del proyecto. - Documentos de pruebas de usabilidad y pilotos. - Registros de campañas y eventos de difusión. - Documentación de certificaciones. | F124: Factores externos que mantienen la estrategia, la Sustentabilidad y las Suposiciones - Disponibilidad de financiamiento semilla / inversión externa. - Capacidad técnica del equipo de desarrollo y socios aliados. - Regulación no impone trabas inesperadas. - Interés de clínicas/EPS en integrarse.

Sheet Arbol Objetivos
B2: ÁRBOL DE OBJETIVOS
B4: Fines Indirectos | D4: Reducir la saturación del sector salud | F4: Reducción de la carga familiar y de cuidadores | H4: Mayor participación en actividades comunitarias | L4: Menor dependencia de servicios asistenciales
B6: Fines Indirectos | D6: Citas más eficientes | F6: Disminución de casos de depresión en adultos mayores | H6: Mayor autonomía personal | L6: Descongestión de EPS y clínicas
B8: Fines Indirectos | D8: Disminución de costos sanitarios | F8: Incremento de las interacciones sociales | H8: Mantenimiento y mejora de capacidades cognitivas | L8: Aumento del bienestar general | P8: Menores periodos de recuperación | Q8: Disminución de fracturas y lesiones graves | R8: Reducción de los costos sanitarios
B10: Fines Directos | C10: . | D10: Aumento de la calidad de vida aplicando tratamientos médicos en momentos oportunos | H10: Reducción de fracturas y lesiones | J10: Mantenimiento de las funciones cognitivas | L10: Mantenimiento de funciones cognitivas, de movilidad y equilibrio | P10: Menor dependencia de servicios asistenciales | Q10: Mejora en la movilidad y el equilibrio | R10: Disminución de fracturas y lesiones graves
B12: Solución Focal/ Proposito Objetivo General | D12: Desarrollar un sistema integral y accesible que prevenga caídas y el deterioro cognitivo en adultos mayores, incremente la adherencia a los ejercicios, ofrezca monitoreo continuo y genere datos clínicos para una atención oportuna y de calidad.
B14: Objetivos específicos | D14: Aumentar la eficacia de los tratamientos médicos | F14: Implementar monitoreo remoto para seguimiento de pacientes | H14: Diseñar programas lúdicos de mejoras cognitivas y prevención de caídas | L14: Facilitar acceso a tecnología adaptada a necesidades particulares
B16: Medios/ Actividades | D16: Herramienta para generación de datos continuos y un análisis de resultados eficientes | H16: Reducir tiempos de espera en citas médicas | J16: Capacitar profesionales en rehabilitación geriátrica | L16: Desarrollar dispositivos accesibles y de bajo costo
B18: Medios/ Actividades | D18: Hacer las citas más eficientes, mediante la prorización basada en los datos | H18: Mejorar la gestión de agenda médica y priorización de casos | J18: Diseñar campañas de prevención y envejecimiento activo | L18: Incentivar la innovación tecnológica en salud
B20: Medios/ Actividades | D20: Garantizar acceso a la salud facilitando tecnología escalable | H20: Garantizar acceso equitativo a programas preventivos | J20: Fomentar hábitos de ejercicio en adultos mayores | L20: Diseño de herramientas que permitan analizar la aparición y el desarrollo sintomas según los casos estudiados
B22: Medios/ Actividades | D22: Reducir la saturación del sector salud mediante un enfoque en la salud preventiva | H22: Otorgar incentivos para proyectos de prevención en salud | J22: Formar talento especializado en geriatría y fisioterapia | L22: Promover alianzas entre gobierno, aseguradoras y sector privado | P22: Revisión de estudios sobre deterioro cognitivo y lo sintomas que lo acompañan

Sheet Analisis PESTEL
B2: ESTUDIO SECTORIAL - ESTRATEGICO
B4: Análisis PESTEL | J4: Herramienta DOFA | N4: Modelo CAME
B6: Descripción | D6: Factor | F6: Detalle | G6: Plazo | J6: Fortalezas (F): | K6: Oportunidades (O): | L6: Debilidades (D): | M6: Amenazas (A): | N6: Estrategias FO: | O6: Estrategias DO: | P6: Estrategias FA: | Q6: Estrategias DA:
G7: Corto plazo (< 1 mes) | H7: Mediano plazo (1 mes a 3 años) | I7: Largo plazo (> 3 años)
B8: Evalúa de qué forma la intervención del gobierno puede afectar la empresa o el proyecto • Cambios de gobierno y sus programas electorales • Política fiscal • Subsidios del gobierno • Guerras y conflictos • Cambios en legislación • Cambios en los tratados comerciales • Acuerdos internacionales • Conflictos internos y externos • Movimientos políticos | D8: Político | E8: Falta de continuidad en políticas públicas | F8: Se puede reducir el presupuesto y desfinanciar los programas de prevención | G8: x | H8: x | M8: x
E9: Cambios en prioridades en salud | F9: Desviación de recursos hacia otras áreas de salud y seguridad. | G9: x | H9: x | M9: x
E10: Interés de gobiernos locales en reducir costos en salud y dependencia | F10: Programas que buscan disminuir el peso económicoque generan hospitalizaciones. El proyecto se puede alinear a estas metas, facilitando acceso a convenios y subsidios | H10: x | K10: x
E11: Posibilidad de alianzas con EPS | F11: El enfoque de los gobiernos a la atención preventiva es una oportunidad para que las EPS vean el proyecto como una forma de reducir costos a largo plazo | I11: x | J11: x | K11: x
B12: Considera cómo el entorno macroeconómico nacional e internacional puede afectar empresa o el proyecto • Tasas de empleo • Ciclo económico • PIB • Impuestos • Inflación • Decisiones económicas de otros gobiernos • Devaluación y reevaluación de la moneda • Tendencias en canales de distribución • Déficit gubernamental • Índice de confianza del consumidor • Financiación • Proteccionismo de los mercados Por ejemplo, la imposición de aranceles por decisión de Donald Trump sobre Toyota hace parte de una variable económica a tener en cuenta. | D12: Económico | E12: Inflación | F12: Puede afectar la capacidd de pago directo de los usuarios. A pesar de esto, el modelo B2B con las EPS puede amortiguar este riesgo. | H12: x | I12: x | M12: x
E13: Baja capacidad de pago directo de adultos mayores | F13: Baja adopción B2C si faltan convenios o subsidios | G13: x | L13: x
E14: Dependencia de financiamiento externo | F14: El proyecto puede dejar de ser sostenible financieramente si no se consolidan usuarios o alianzas con las entidades de salud | G14: x | L14: x
E15: Modelo de financiación con EPS | F15: El sistema de salud del país permite que las EPS cubran tecnologías de prevención costo-eficientes. Esto abre la oportunidad a la financiación de los dispositivos para los clientes. | H15: x | I15: x | K15: x
E16: Creciente gasto público en salud | F16: Cada caida implica gastos para el sistema de salud. La presentación de este proyecto que busca reducir incidentes puede ser altamente atractiva. | I16: x | K16: x
E17: Crecimiento del mercado potencial | F17: ∼14 % de la población colombiana tiene más de 60 años, y para 2040 se espera que llegue al 20 %. | I17: x | K17: x
B18: Evalúa cultura, religión, creencias, hábitos, preferencias, etc. • Nivel de educación • Modas • Patrones de compra • Creencias • Religiones • Opinión de los clientes • Opiniones o percepción de los medios de información • Estilo de vida • Nivel de ingresos • Nivel de edad | D18: Social | E18: Resistencia al uso de tecnología en adultos mayores | F18: Posiblemente exista una baja adherencia inicial | G18: x | M18: x
E19: Desigualdad en acceso digital | F19: Adultos mayores con bajos ingresos o en zonas alejadas podrían no tener smartphones compatibles | G19: x | H19: x | L19: x
E20: Nivel de educación digital de cuidadores/familiares | F20: Si es bajo, puede frenar la implementación. | G20: x | L20: x
E21: Mayor interés de familias en soluciones accesibles | F21: Mayor busqueda de opciones prácticas que se puedan usar en casa sin necesidad de largos desplazamientos | H21: x | I21: x | K21: x
E22: Mayor adopción digital | F22: El acceso a smartphones en la población general crece cada año, esto permite una curva de aprendizaje más baja. | H22: x | I22: x | K22: x
E23: Valor social de la autonomía | F23: El fuerte componente emocional y cultural en preservar la independencia de adulto mayor. Una propuesta que retrase el deterioro puede ser altamente valorada | G23: x | J23: x
B24: El reto que trae está en que la empresa o los involucrados del proyecto sean consientes de qué tipo de tecnologías la pueden beneficiar o impactar negativamente • Machine Learning • Nuevos códigos de programación • Nueva maquinaria o dispositivos tecnológicos • Impresión 3D • Uso de la energía • Reemplazo de tecnología • Software en la nube • Obsolescencia • Internet • Incentivos por uso de tecnologías | D24: Tecnológico | E24: Obsolescencia tecnológica | F24: La rapidez de innovación obliga a diseñar un dispositivo actualizable y escaclabel para evitar el rezago frente a competidores. | H24: x | I24: x | M24: x
E25: Machine learning | F25: Permite personalizar el nivel deexigencia y adaptarse al progreso del usuario. | G25: x | J25: x
E26: Telemedicina y analítica de datos | F26: El aumento de la atención remota valida la potencialidad que tiene el proyecto al generar reportes en tiempo real. | G26: x | J26: x
E27: Integracion con telefonos móviles | F27: El uso generalizado de smartphones hace que la plataforma sea accesible sin necesidad de hardware muy especializado y costoso. | G27: x | J27: x
E28: Avances en sensores de movimiento | F28: Dispositivos cada vez más pequeños y más económicos que posibilitan medir con precisión. | G28: x | K28: x
B29: Evalúa de qué forma el medio ambiente afecta a la empresa o el proyecto • Cambio climático • Consumo de recursos no renovables • Reciclaje • Contaminación • Políticas medioambientales • Gases líquidos • Riesgos naturales | D29: Ambiental
B34: Las empresas deben cumplir si o si la ley y esta cambia constantemente. A veces no solo aplica la ley del país donde está la empresa o el proyecto, también aplica la ley del país donde se desea estar. • Propiedad intelectual • Salud y seguridad laboral • Regulación de sectores • Leyes de protección • Salario mínimo • Licencias | D34: Legal | E34: Regulación INVIMA | F34: El sistema actualmente clasificaría como un dispositivo clase I, pudiendo llegar a clase II. posibles cambios en esta clasificación podrian impactar el proyecto | G34: x | J34: x
E35: Protección de datos clínicos | F35: El sistema manejará información sensible, por lo que debe cumplir con la Ley 1581 de 2012 en Colombia y con estándares internacionales (HIPAA, GDPR) si se escala. | G35: x | J35: x
E36: Propiedad intelectual | F36: Tanto el software como los diseños de hardware pueden protegerse para crear barreras de entrada frente a competidores | G36: x | K36: x

Sheet Ejemplo PESTEL
A1: Análisis PESTEL
A3: Factor | C3: Detalle | D3: Plazo
D4: Corto plazo (1 mes o menos) | E4: Mediano plazo (de 1 a 3 años) | F4: Largo plazo (más de 3 años) | G4: Fortalezas (F): | H4: Oportunidades (O): | I4: Debilidades (D): | J4: Amenazas (A):
A5: Político | B5: Cambio de presidente | C5: El programa de gobierno se adecua a las necesidades y expectativas de la empresa | D5: X | G5: x
B6: Las elecciones políticas de alcaldes y gobernadores | C6: Uno de los candidatos en la empresa trabajó para la competencia e inició un pleito legal por la patente del dosificador de agua | E6: X | I6: x
B7: Tratados comerciales | C7: Se planea tratado comercial con los países centroaméricanos para exportar nuestros productos | D7: X
A8: Económico | B8: Divisa | C8: La devaluación de nuestra moneda frente al dólar ha aumentado el precio de la materia prima por la fabricación de nuestros productos en un 15% | D8: X
B9: Aumento de la tasa de interés | C9: Debido al aumento de la tasa de interés la empresa no ha cumplido con su plan de inversiones, pues se requiere financiamiento de los bancos | D9: X
B10: Aumento en las exportaciones | C10: Los tratados de libre comercio del año pasado han permitido aumentar los ingresos por el concepto de exportaciones a Sudamérica | D10: X
A11: Social | B11: Aumento de la conciencia por el autocuidado | C11: Al analizar las fuentes de las ventas, un 20% indica que se han sido por autocuidado y por el conocimiento de los beneficios del agua mineral | E11: X
A12: Tecnológico | B12: Impresión 3D | C12: Puede ser posible que se realice la impresión de ciertos componentes de los filtros de agua, lo que podría optimizar los tiempos de producción y los costos | E12: X
B13: Robo de información electrónica | C13: Se perdió el 20% de información del proceso jurídico por la apertura indebida de un correo. Se establece como un riesgo no tratado ya que es la primera vez que ocurre | D13: X
A14: Ambiental | B14: Huella de carbono | C14: Se está trabajando para obtener la certificación de carbono neutro | D14: X
B15: Residuos | C15: La transformación de los residuos de producción toma tiempo y es costosa para la empresa | E15: X
A16: Legal | B16: Decreto 1072 | C16: La empresa debe dar cumplimiento al decreto 1072 que establece el SG-SST | D16: X

Sheet Estudio de Mercado-Encuesta
B2: Se desea iniciar la formulación y evaluación de un proyecto de inversión que tiene como objetivo desarrollar una aplicación móvil llamada Equilibrado+, diseñada para apoyar a personas con discapacidad en su vida diaria mediante recordatorios, reportes de caídas, rutinas de ejercicios y acompañamiento digital. Para tal fin, se realizará una investigación en la ciudad de Medellín, teniendo en cuenta que, según los registros oficiales, la población con alguna discapacidad asciende aproximadamente a 315.000 personas. a. Suponga que desea hacer la encuesta con un 95% de confianza (Z=1,96), un margen de error del 5%. ¿Cuántas encuestas debe realizar?
B5: Nivel de confianza: | C5: Z | D5: 1.96
B6: Error máximo tolerable | C6: e | D6: 0.05
B7: Poblacion | C7: N | D7: 315000 | E7: Poblacion aporx adultos mayores Medellín
B8: Desviación | C8: S | D8: 0.5
B9: Numero de Encuestas (n) | D9: =(D7*D8*D8*D5*D5)/((D6*D6*(D7-1)+D8*D8*D5*D5)) -> 383.69328
B12: De la encuesta realizada a 100 personas en la ciudad de Medellín, se vio que un porcentaje significativo mostró interés del producto para el apoyo en la vida diaria de personas con discapacidad. Las personas encuestadas indicaron que, de las funcionalidades de mayor preferencia, destacan las alertas y recordatorios (30%), el reporte de caídas (25%), las rutinas de ejercicios guiados (20%), la facilidad de uso (15%) y, finalmente, contar con un precio accesible (10%).
B15: Alertas y recordatorios | C15: 0.3 | D15: Se hicieron 100 encuestas
B16: El reporte de caídas | C16: 0.25
B17: las rutinas de ejercicios guiados (20%), la facilidad de uso (15%) y, finalmente, contar con un precio accesible (10%). | C17: 0.2 | D17: =SUM(C15:C19) -> 1
B18: la facilidad de uso | C18: 0.15
B19: Contar con un precio accesible | C19: 0.1
C22: Sesiones ejercicio | D22: Alertas activadas | E22: Descargas reporte | F22: Recordatorio diario
B23: Cantidad | C23: 5 | D23: 1 | E23: 1 | F23: 1
B24: Frecuencia | C24: por sesion | D24: Mensual | E24: Mensual | F24: Diario
B26: Población Objetivo: | C26: Población estrato 2, 3, 4, 5 y 6 de la ciudad de Medellin | E26: % Personas comprarian | F26: 0.6
B27: N: Tamaño Población | C27: =D7 -> 315000
B28: n: Tamaño Muestra | C28: =100 -> 100 | D28: 100
B30: Pregunta | C30: Enunciado | D30: Respuesta | E30: Personas | F30: %
B31: 1 | C31: Dispuesto a comprar | D31: Sí | E31: =C28*F26 -> 60 | F31: =E31/C28 -> 0.6
D32: No | E32: =+C28-E31 -> 40 | F32: =E32/C28 -> 0.4
B33: 2 | C33: Estrato socioeconómico | D33: 3 | E33: 40 | F33: =+E33/$C$28 -> 0.4
D34: 4 | E34: 12 | F34: =+E34/$C$28 -> 0.12
D35: 5 | E35: 26 | F35: =+E35/$C$28 -> 0.26
D36: 6 | E36: 22 | F36: =+E36/$C$28 -> 0.22 | G36: =C28-E37 -> 0
B37: 3 | C37: Frecuencia de compra | E37: =SUM(E33:E36) -> 100 | F37: =SUM(F33:F36) -> 1
B39: PROYECCIÓN DE DEMANDA SEGÚN ENCUESTA
B41: Población | C41: =+D7 -> 315000
B42: % Población Estrato 4,5,6 | C42: =F34+F35+F36 -> 0.6
B43: Población Estrato 4,5,6 que compra | C43: =+C41*C42 -> 189000
B45: % Población Sí compra | C45: =+F31 -> 0.6
B46: Población Estrato 4,5,6 que compra | C46: =+C43*C45 -> 113400
B49: Datos Encuesta | E49: Proyección Personas | F49: Proyección Mes | G49: Proyección Año
B50: APP | C50: 1 | E50: =C46*C50 -> 113400 | F50: =E50*1 -> 113400 | G50: =F50*12 -> 1360800
B52: AÑO | C52: Poblacion Mayor a 65 años | D52: CRECIMIENTO
B53: 2025 | C53: 315329
B54: 2026 | C54: 318597 | D54: =+C54/C53-1 -> 0.010363779 | I54: Esta es la pryeccion de suscripciones, no es igual al numero de usuarios, sino la cantidad de veces que el usuario pago en el año
B55: 2027 | C55: 322031 | D55: =+C55/C54-1 -> 0.010778507
B56: 2028 | C56: 325477 | D56: =+C56/C55-1 -> 0.010700833
B57: 2029 | C57: 329023 | D57: 0.0196
B60: Proyección de Suscripciones
C62: 2025 | D62: =+C62+1 -> 2026 | E62: =+D62+1 -> 2027 | F62: =+E62+1 -> 2028 | G62: =+F62+1 -> 2029 | H62: =+G62+1 -> 2030
C63: 1 | D63: 2 | E63: 3 | F63: 4 | G63: 5 | H63: 6
B64: APP | C64: =G50 -> 1360800 | D64: =C64+C64*D54 -> 1374903 | E64: =D64+D64*D55 -> 1389722.4 | F64: =E64+E64*D56 -> 1404593.6 | G64: =F64+F64*D57 -> 1432123.7 | H64: =G64+G64*E57 -> 1432123.7

Sheet Est.Merca-participacion
B2: Variaciones Porcentuales
B6: Marca | C6: Año de inicio | D6: Instalaciones año inicial | E6: Instalaciones 2024 | F6: Tasa de crecimiento anual compuesta | H6: Formula de la tasas de crecimeinto anual compuesta:
B7: Thera-Trainer | C7: 2010 | D7: 50 | E7: 100000 | F7: =(E7/D7)^(1/(2024-C7))-1 -> 0.72102769
B8: One Step | C8: 2016 | D8: 50 | E8: 10000 | F8: =(E8/D8)^(1/(2024-C8))-1 -> 0.93922745

Sheet Mapa de Empatía

Sheet costos, gastos,inversiones
B3: Condiciones de mercado
B4: Costos de desarrollo tecnologico
B5: Precio de venta del producto (suscripción mensual)
B6: Capacidad servidores
B8: Precio de materiales e insumos
B9: Servidores
B10: • Políticas de crédito
B13: Inversion en activos fijos
B14: Infraestructira digital
B15: Equipod de oficina
B18: capacidad de produccion
B19: capacidad de produccion maxima
... B80: indica la necesidad de dinero de una empresa para poder cumplir con sus operaciones

Sheet Analisis tecnico
A2: ESTUDIO TÉCNICO
A4: FORMATO DE EVALUACIÓN TÉCNICA
A6: ITEM | B6: Características técnicas a evaluar | F6: Resultado
A7: 1 | B7: ¿Cuáles son las nuevas tecnologías necesarias para el desarrollo, la implementación y las operaciones del nuevo producto o proyecto? | F7: Combinación y formulación de materias primas para el cumplimiento de las especificaciones
A11: 2 | B11: ¿Se cuenta con todo el conocimiento necesario el para el desarrollo, la implementación y las operaciones del nuevo producto o proyecto? | F11: No
A15: 3 | B15: ¿Qué conocimientos no se poseen, y es factible desarrollarlos o adquirirlos durante la ejecucción y puesta en marcha del proyecto?, incluir los conocimientos que deben ser desarrollados por el personal. | F15: Estabilidad de productos y adherencia para productos que cumplan bajos ciclos de horneo
A19: 4 | B19: ¿Se cuenta con todas las herramientas necesarias el para el desarrollo, la implementación y las operaciones del nuevo producto o proyecto? | F19: Si
A23: 5 | B23: ¿Qué herramientas hacen falta, y es factible económicamente conseguirlas?, o que nuevos dispositivos deben ser desarrolados | F23: N/A
A27: 6 | B27: ¿Se cuenta con todas las habilidades necesarias para el desarrollo, la implementación y las operaciones del nuevo producto o proyecto? | F27: Si
A31: 7 | B31: ¿Qué habilidades no se poseen, y es factible económicamente desarrolladas? | F31: N/A
A35: 8 | B35: ¿Con que experiencia se cuenta en las tecnologías necesarias para el desarrollo y puesta en marcha del nuevo desarrollo? | F35: La compañía produce productos similares, adecuando la tecnología de acuerdo a las materias primas disponibles desde hace 30 años
A39: 9 | B39: ¿La reglamentación que limitantes técnicos aporta?, Estamos en capadidad de realizar el desarrollo cumpliendo con las reglamentacones existentes? | F39: La reglamentación es la misma que se tiene para los productos que se entregan actualmente y que serán reemplazados por esta nueva técnologia
A43: 10 | B43: ¿Cuáles son las innovaciones en producto y procesos que serán desarroladas con el proyecto? | F43: Capacidad de cumpliento de especificaciones a bajas condiciones de horneo
A47: 11 | B47: ¿Hay patentes que limitan el producto a desarrollar?, ¿Qué limitantes, imponen las patentes existentes?, es factible que el producto a desarrollar evite las limitaciones impuestas por las patentes? | F47: no
A51: 12 | B51: ¿Cuánto tiempo es necesario para la puesta en marcha del proyecto, teniendo en cuenta del desarrollo de las nuevas capacidades, tecnológicas y humanas? | F51: 6 meses
... A67: 16 | B67: ¿Cuál es el impacto medio ambiental del proyecto?, ¿Tienen en cuenta reducción de materiales contaminantes? | F67: Los productos deben cumplir con la reglamentación de materias primas provistas por el cliente y su casa matriz

Sheet SELECCION-LOCALIZACIÓN
A4: ESTUDIO TÉCNICO
A7: CRITERIO | B7: PESO /100 | C7: ALTERNATIVA 1 | E7: ALTERNATIVA 2
C8: CALIFICACIÓN | D8: PONDERACIÓN | E8: CALIFICACIÓN | F8: PONDERACIÓN
C9: /5 | E9: /5
A10: CLIENTES
A11: COSTOS
A12: IMPUESTOS
A13: PERSONEL DISPONIBLE
A14: ABASTECIMIENTO
A15: TOTALES | B15: SUMA=100% | D15: SUMA | F15: SUMA

Sheet FLUJO GRAMA 
A1: FLUJO GRAMA DEL PROCESO
B5: PROCESO
B17: #VALUE!
A37: ACTIVIDAD DEL PROCESO | B37: DESCRIPCION | C37: MAQUINARIA | D37: CANTIDAD | E37: VALOR | F37: VALOR TOTAL | G37: EQUIPOS | H37: VALOR | I37: CANTIDAD | J37: VALOR TOTAL | K37: MUEBLES Y ENSERES | L37: VALOR | M37: CANTIDAD | N37: VALOR TOTAL | O37: MATERIALES E INSUMOS | P37: VALOR | Q37: CANTIDAD | R37: VALOR TOTAL | S37: PERSONAL | T37: SALARIO | U37: CANTIDAD | V37: VALOR TOTAL | W37: PERMISOS -LICENCIAS | X37: VALOR | Y37: CANTIDAD | Z37: VALOR TOTAL
C38: Horno Rotatorio Panadería | D38: 1 | E38: 17500000 | F38: =+D38*E38 -> 17500000 | H38: 4000000 | I38: 1 | J38: =+H38*I38 -> 4000000 | K38: mesa | L38: 3000000 | M38: 1 | N38: =+L38*M38 -> 3000000 | O38: Papel | S38: OPERAC | T38: 2000000 | U38: 1 | V38: =+T38*U38 -> 2000000
C39: Batidoras Industriales | D39: 1 | E39: 5000000 | F39: =+D39*E39 -> 5000000
C40: Balanza | D40: 1 | E40: 600000 | F40: =+D40*E40 -> 600000
C41: Tajadora de pan | D41: 1 | E41: 10500000 | F41: =+D41*E41 -> 10500000
C42: Cortadora divisora de masa | D42: 1 | E42: 8520000 | F42: =+D42*E42 -> 8520000
C43: Amasadora | D43: 1 | E43: 8000000 | F43: =+D43*E43 -> 8000000
C44: Enfriador | D44: 1 | E44: 1800000 | F44: =+D44*E44 -> 1800000
C45: Carros escabiladeros | D45: 1 | E45: 1200000 | F45: =+D45*E45 -> 1200000
C46: Mesas (Proceso Productivo) | D46: 3 | E46: 1500000 | F46: =+D46*E46 -> 4500000
C47: Moldes, recipientes y utensilios | D47: 1 | E47: 500000 | F47: =+D47*E47 -> 500000
C48: Vitrinas Panadería y Pastelería | D48: 1 | E48: 6500000 | F48: =+D48*E48 -> 6500000
C49: Caja Registradora | D49: 1 | E49: 900000 | F49: =+D49*E49 -> 900000
C50: Computadores | D50: 4 | E50: 2000000 | F50: =+D50*E50 -> 8000000
... C52: Sillas | D52: 11 | E52: 72000 | F52: =+D52*E52 -> 792000
A53: TOTAL | C53: Sillas Gerenciales | D53: 5 | E53: 125000 | F53: =SUM(F38:F52) -> 78032000 | J53: =SUM(J38:J52) -> 4000000 | N53: =SUM(N38:N52) -> 3000000 | R53: =SUM(R38:R52) -> 0 | V53: =SUM(V38:V52) -> 2000000 | Z53: =SUM(Z38:Z52) -> 0
A56: CAPACIDAD MAXIMA PRODUCCION / PRESTACIÓN DEL SERVICIO | G56: PROYECCION DEMANDA | K56: DESFASE
B57: MAXIMO PRODUCCION / PRESTACION SERVICIO | C57: DIA | D57: SEMANA | E57: MES | F57: AÑO | G57: DIA | H57: SEMANA | I57: MES | J57: AÑO
A58: MAQUINARIA
A59: PERSONAL

Sheet inversiones
A2: Activos / Recursos Digitales | B2: Cantidad | C2: Precio Unitario [2025] | D2: VALOR TOTAL
A3: Desarrollo inicial de APP (versión básica con login, catálogo de productos y carrito de compras) | B3: 1 | C3: 12000000 | D3: 12000000
A4: Servidor Cloud / Hosting por 12 meses | B4: 1 | C4: 5000000 | D4: 5000000
A5: Software (licencias básicas: CRM, contabilidad, diseño) | B5: 1 | C5: 3000000 | D5: 3000000
A6: Pasarela de pagos (integración) | B6: 1 | C6: 500000 | D6: 500000
A7: Diseño de interfaz (branding, UX básico) | B7: 1 | C7: 2000000 | D7: 2000000
A8: Mantenimiento y soporte (primer año) | B8: 1 | C8: 2500000 | D8: 2500000
A9: Marketing digital inicial (lanzamiento y prueba de mercado) | B9: 1 | C9: 3000000 | D9: 3000000
A10: Dispositivos de prueba (celulares/tabletas para testeo) | B10: 2 | C10: 1200000 | D10: 2400000
A11: Computadores de desarrollo (ingenieros, diseño, IA) | B11: 3 | C11: 3000000 | D11: 9000000
A12: Laptops administrativas / comerciales | B12: 2 | C12: 2000000 | D12: 4000000
A13: Escritorios operativos | B13: 5 | C13: 900000 | D13: 4500000
A14: Sillas ergonómicas | B14: 5 | C14: 500000 | D14: 2500000
... A17: Tablets para validación con usuarios / EPS | B17: 10 | C17: 800000 | D17: 8000000
C18: Total Activos | D18: =SUM(D3:D17) -> 62600000

Sheet C. inversiones y costos ctables
A3: ESTUDIO TÉCNICO
A5: INVERSIONES Y COSTOS CONTABLES
A7: Item | B7: Cantidades | C7: Año 0 | F7: Costos contables
A8: DESCRIPCION | B8: CANTIDADES | C8: VALOR DE COMPRA | D8: VALOR TOTAL | E8: TIEMPO DEPRECIACION | F8: Año 1 | G8: Año 2 | H8: Año 3 | I8: Año 4 | J8: Año 5 | K8: DEPRECIACION ACUMULADA Sumatoria de los años de uso | L8: Valor en libros al final del año 5 Valor de compra (-) Depreciación acumulada | M8: Valor de venta del activo | N8: Ganancia/Pérdida en Venta de activos fijos
A9: =inversiones!A5 -> Software (licencias básicas: CRM, contabilidad, diseño) | B9: =inversiones!B5 -> 1 | C9: =inversiones!C5 -> 3000000 | D9: =inversiones!D5 -> 3000000 | E9: 5 | F9: =$D9/$E9 -> 600000 | G9: =$D9/$E9 -> 600000 | H9: =$D9/$E9 -> 600000 | I9: =$D9/$E9 -> 600000 | J9: =$D9/$E9 -> 600000 | K9: =SUM(F9:J9) -> 3000000 | L9: =D9-K9 -> 0 | M9: =L9 -> 0 | N9: =+M9-L9 -> 0
A10: =inversiones!A10 -> Dispositivos de prueba (celulares/tabletas para testeo) | B10: =inversiones!B10 -> 2 | C10: =inversiones!C10 -> 1200000 | D10: =inversiones!D10 -> 2400000 | E10: 5 | F10: =$D10/$E10 -> 480000 | G10: =$D10/$E10 -> 480000 | H10: =$D10/$E10 -> 480000 | I10: =$D10/$E10 -> 480000 | J10: =$D10/$E10 -> 480000 | K10: =SUM(F10:J10) -> 2400000 | L10: =D10-K10 -> 0 | M10: =L10 -> 0 | N10: =+M10-L10 -> 0
A11: =inversiones!A11 -> Computadores de desarrollo (ingenieros, diseño, IA) | B11: =inversiones!B11 -> 3 | C11: =inversiones!C11 -> 3000000 | D11: =inversiones!D11 -> 9000000 | E11: 5 | F11: =$D11/$E11 -> 1800000 | G11: =$D11/$E11 -> 1800000 | H11: =$D11/$E11 -> 1800000 | I11: =$D11/$E11 -> 1800000 | J11: =$D11/$E11 -> 1800000 | K11: =SUM(F11:J11) -> 9000000 | L11: =D11-K11 -> 0 | M11: =L11 -> 0 | N11: =+M11-L11 -> 0
A12: =inversiones!A12 -> Laptops administrativas / comerciales | B12: =inversiones!B12 -> 2 | C12: =inversiones!C12 -> 2000000 | D12: =inversiones!D12 -> 4000000 | E12: 5 | F12: =$D12/$E12 -> 800000 | G12: =$D12/$E12 -> 800000 | H12: =$D12/$E12 -> 800000 | I12: =$D12/$E12 -> 800000 | J12: =$D12/$E12 -> 800000 | K12: =SUM(F12:J12) -> 4000000 | L12: =D12-K12 -> 0 | M12: =L12 -> 0 | N12: =+M12-L12 -> 0
A13: =inversiones!A13 -> Escritorios operativos | B13: =inversiones!B13 -> 5 | C13: =inversiones!C13 -> 900000 | D13: =inversiones!D13 -> 4500000 | E13: 10 | F13: =$D13/$E13 -> 450000 | G13: =$D13/$E13 -> 450000 | H13: =$D13/$E13 -> 450000 | I13: =$D13/$E13 -> 450000 | J13: =$D13/$E13 -> 450000 | K13: =SUM(F13:J13) -> 2250000 | L13: =D13-K13 -> 2250000 | M13: =L13 -> 2250000 | N13: =+M13-L13 -> 0
A14: =inversiones!A14 -> Sillas ergonómicas | B14: =inversiones!B14 -> 5 | C14: =inversiones!C14 -> 500000 | D14: =inversiones!D14 -> 2500000 | E14: 10 | F14: =$D14/$E14 -> 250000 | G14: =$D14/$E14 -> 250000 | H14: =$D14/$E14 -> 250000 | I14: =$D14/$E14 -> 250000 | J14: =$D14/$E14 -> 250000 | K14: =SUM(F14:J14) -> 1250000 | L14: =D14-K14 -> 1250000 | M14: =L14 -> 1250000 | N14: =+M14-L14 -> 0
A15: =inversiones!A15 -> Router y red local | B15: =inversiones!B15 -> 1 | C15: =inversiones!C15 -> 1200000 | D15: =inversiones!D15 -> 1200000 | E15: 5 | F15: =$D15/$E15 -> 240000 | G15: =$D15/$E15 -> 240000 | H15: =$D15/$E15 -> 240000 | I15: =$D15/$E15 -> 240000 | J15: =$D15/$E15 -> 240000 | K15: =SUM(F15:J15) -> 1200000 | L15: =D15-K15 -> 0 | M15: =L15 -> 0 | N15: =+M15-L15 -> 0
A16: =inversiones!A16 -> Pantallas para monitoreo de alertas | B16: =inversiones!B16 -> 2 | C16: =inversiones!C16 -> 1500000 | D16: =inversiones!D16 -> 3000000 | E16: 5 | F16: =$D16/$E16 -> 600000 | G16: =$D16/$E16 -> 600000 | H16: =$D16/$E16 -> 600000 | I16: =$D16/$E16 -> 600000 | J16: =$D16/$E16 -> 600000 | K16: =SUM(F16:J16) -> 3000000 | L16: =D16-K16 -> 0 | M16: =L16 -> 0 | N16: =+M16-L16 -> 0
A17: =inversiones!A17 -> Tablets para validación con usuarios / EPS | B17: =inversiones!B17 -> 10 | C17: =inversiones!C17 -> 800000 | D17: =inversiones!D17 -> 8000000 | E17: 5 | F17: =$D17/$E17 -> 1600000 | G17: =$D17/$E17 -> 1600000 | H17: =$D17/$E17 -> 1600000 | I17: =$D17/$E17 -> 1600000 | J17: =$D17/$E17 -> 1600000 | K17: =SUM(F17:J17) -> 8000000 | L17: =D17-K17 -> 0 | M17: =L17 -> 0 | N17: =+M17-L17 -> 0
C18: =inversiones!C18 -> Total Activos | D18: =SUM(D9:D17) -> 37600000 | F18: =SUM(F9:F17) -> 6820000 | G18: =SUM(G9:G17) -> 6820000 | H18: =SUM(H9:H17) -> 6820000 | I18: =SUM(I9:I17) -> 6820000 | J18: =SUM(J9:J17) -> 6820000 | K18: Valor en libros | L18: =SUM(L9:L17) -> 3500000
D19: =inversiones!D18 -> 62600000
A21: DEPRECIACION = (VALOR DEL ACTIVO -VALOR SALVAMENTO)/NRO AÑOS A DEPRECIAR
A22: DEPRECIACION ACUMULADA= VALOR DEPRECIACION DEL AÑO ACTUAL + DEPRECIACION ACUMULADA AÑO ANTERIOR
A23: VALOR LIBROS= VALOR DEL ACTIVO _ DEPRECIACION ACUMULADA
A24: GANACIA O PERDIDA = VALOR EN LIBROS - VALOR VENTA

Sheet Identificación de costos
B2: ESTUDIO TECNICO-ESTUDIO DE COSTOS
B4: Costos Variables
B6: Equilibrio+
B7: Materia Prima (Costo DIRECTO) | C7: Requerimiento | D7: Costo 2025
B8: Pasarela de pagos | C8: configuracion + integracion (comisión por pago) | D8: 30000
B11: Materia Prima (Costo Indirecto) | C11: Requerimiento | D11: Costo 2025
B12: Licencia App Store / Google Play | C12: Anual (prorrateado mensual) | D12: 90000
B13: Marketing digital inicial | C13: Campana minima redes sociales | D13: 500000
B14: Soporte tecnico (horas freelance) | C14: 20 hrs mes | D14: 400000 | E14: =SUM(D12:D14) -> 990000
B17: COSTO VARIABLE UNITARIO | D17: =SUM(D8:D8)+ SUM(D12:D14) -> 1020000
I19: =+SUM('[1]2.A. Estudio Inversiones'!G7:G13) -> 51920000
B20: Costos Laborales de produccion ( desarrollo + soporte tecnico)
I21: proyeccion suscripciones
B22: Empleado | C22: # Empleados | D22: Salario Mensual 2024 | E22: Carga prestacional | F22: Salario Mensual con Factor Prestacional 2025 | G22: Costo ANUAL Nómina 2025 | H22: Observacion | I22: 10000
B23: Jefe de tecnologia (CTO) | C23: 1 | D23: ='Plantilla Nomina'!C8 -> 10000000 | E23: ='Plantilla Nomina'!O8 -> 5093866.7 | F23: =D23+E23 -> 15093867 | G23: =+F23*12 -> 181126400 | I23: =G23/$I$22 -> 18112.64
B24: Desarrollador Full-Stack | C24: 2 | D24: ='Plantilla Nomina'!C9 -> 4500000 | E24: ='Plantilla Nomina'!O9 -> 2292240 | F24: =D24+E24 -> 6792240 | G24: =+F24*12 -> 81506880 | I24: =G24/$I$22 -> 8150.688
B25: Disenyador UX/UI | C25: 1 | D25: 2400000 | E25: 1456028 | F25: =D25+E25 -> 3856028 | G25: =+F25*12 -> 46272336 | I25: =G25/$I$22 -> 4627.2336
B26: Soporte tecnico | C26: 1 | D26: 1750000 | E26: 1124926.7 | F26: =D26+E26 -> 2874926.7 | G26: =+F26*12 -> 34499120 | I26: =G26/$I$22 -> 3449.912
B27: TOTAL COSTO MANO DE OBRA PRODUCCION | G27: =SUM(G23:G26) -> 343404736 | I27: =SUM(I23:I26) -> 34340.474
B29: Gastos Laborales administracion
B31: Empleado | C31: # Empleados | D31: Salario Mensual 2024 | E31: Carga prestacional | F31: Salario Mensual con Factor Prestacional 2025 | G31: Costo ANUAL Nómina 2025
B32: Gerente General | C32: 1 | D32: 4000000 | E32: 2037546.7 | F32: =D32+E32 -> 6037546.7 | G32: =+F32*12 -> 72450560
B33: Coordinador de Marketing | C33: 1 | D33: 2500000 | E33: 1506966.7 | F33: =D33+E33 -> 4006966.7 | G33: =+F33*12 -> 48083600
B34: Community Manager | C34: 1 | D34: 1800000 | E34: 1150396 | F34: =D34+E34 -> 2950396 | G34: =+F34*12 -> 35404752
B35: Contador | C35: 1 | D35: 2000000 | E35: 1252273.3 | F35: =D35+E35 -> 3252273.3 | G35: =+F35*12 -> 39027280
B36: Personal de Aseo Administrativo | C36: 1 | D36: 1423500 | E36: 958611.92 | F36: =D36+E36 -> 2382111.9 | G36: =+F36*12 -> 28585343
B37: TOTAL GASTOS LABORALES ADMINISTRATIVO | G37: =SUM(G32:G36) -> 2.2355154e+08
B40: GASTOS DE OPERACION FIJOS ANUALES
B42: Rubro | C42: Periodicidad | E42: Periodicidad/Año | F42: Costo POR PERIODO 2025 | H42: Costo ANUAL 2025 | I42: PERIODICIDAD
B43: Arrendamiento | C43: Mensual | E43: 12 | F43: 2000000 | H43: =+F43*E43 -> 24000000 | I43: Mensual | J43: CFT
B44: Servicios Públicos | C44: Mensual | E44: 12 | F44: 600000 | H44: =+F44*E44 -> 7200000 | I44: Mensual | J44: CFT
B45: Hosting y servidores cloud (AWS) | C45: Mensual | E45: 12 | F45: 350000 | H45: =+F45*E45 -> 4200000 | I45: Trimestral | J45: CFT
B46: Mantenimiento Equipos (laptops, tablets) | C46: Trimestral | E46: 4 | F46: 800000 | H46: =+F46*E46 -> 3200000 | I46: Mensual | J46: CFT
B47: Plan software administrativo (CRM, Contabilidad, gestion de usuarios) | C47: Mensual | E47: 12 | F47: 300000 | H47: =+F47*E47 -> 3600000
B48: Seguros | C48: Anual | E48: 1 | F48: 5000000 | H48: =+F48*E48 -> 5000000
B49: TOTAL GASTOS DE OPERACIÓN FIJOS | H49: =SUM(H43:H48) -> 47200000
B57: Costo de Producción-Costo variable | E57: Equilibrado+
C58: Materia prima directa (MD) | E58: =D8 -> 30000
C59: costos indiractod de fabricacion CIF | E59: =E14 -> 990000
C60: Mano de obra Directa (MOD) | E60: =+I27 -> 34340.474
B61: TOTAL COSTOS DE PRODUCCION O PRESTACION DEL SERVICIO | E61: =SUM(E58:E60) -> 1054340.5
C63: Gastos de operación
C65: Gastos de operación anuales totales | D65: =+H49 -> 47200000
D69: Equilibrado+ | E69: ventas totales
C70: Proyeccion de ventas | D70: =+I22 -> 10000 | E70: =SUM(D70:E70) -> 0
C71: unidades total a vender
C72: participacion ventas | D72: 1
C73: Gastos operacionales Me totales | D73: =+D65*D72 -> 47200000
C74: Gastos operacionales Me Unitarios | D74: =+D73/D70 -> 4720
C76: Calculo del precio venta
C78: Precio
C80: Equilibrio+ | D80: 0.03 | F80: * Margen operativo porque en el costo unitario se incluyeron todos los costos y gastos del proyecto
D84: Equilibrio+
C85: CVU | D85: =+E61 -> 1054340.5
C86: Costos totales Medio | D86: =+D74 -> 4720
C87: Margen de utilidad requerida | D87: =D80 -> 0.03
C88: PVP Año 1 | D88: =+(D85+D86)/(1-D87) -> 1091814.9

Sheet Punto de equilibrio
A2: ESTUDIO TÉCNICO
A4: Punto de equilibrio
B5: UNIDADES VENTA PROYECTADA
A6: Equilibrado+ | B6: =+'Identificación de costos'!D70 -> 10000
C8: participacion en la venta
A9: gato totale total | C9: Equilibrado+
C10: =+'Identificación de costos'!D72 -> 1
B11: =+'Identificación de costos'!D65 -> 47200000 | C11: =+B11*C10 -> 47200000
A12: Depreciacion Anual | B12: ='C. inversiones y costos ctables'!F19 -> 0 | C12: =+B12*'Identificación de costos'!D72 -> 0
B14: Equilibrado+
A15: Costos totales | B15: =+C11 -> 47200000
A16: Depreciación | B16: =+C12 -> 0
A17: PVP | B17: =+'Identificación de costos'!D88 -> 1091814.9
A18: CVU | B18: =+'Identificación de costos'!D85 -> 1054340.5 | E18: =+B17-B18 -> 37474.448
A19: Q* | B19: =+(B15+B16)/(B17-B18) -> 1259.5249
A21: PROYECCION VENTAS | B21: =+'Identificación de costos'!I22 -> 10000
A22: DIFERENCIA | B22: =+B21-B19 -> 8740.4751
A24: PRUEBA | E24: PRUEBA
A25: INGRESOS | B25: =+B19*B17 -> 1.3751681e+09 | E25: INGRESOS | F25: =+B21*B17 -> 1.0918149e+10
A26: COSTOS DE PRODUC | B26: =+B18*B19 -> 1.3279681e+09 | E26: COSTOS DE PRODUC | F26: =+B21*B18 -> 10543404736
A27: UTILIDAD BRUTA | B27: =+B25-B26 -> 47200000 | E27: UTILIDAD BRUTA | F27: =+F25-F26 -> 3.7474448e+08
A28: COSTOS FIJOS | B28: =+B15 -> 47200000 | E28: COSTOS FIJOS | F28: =+B28 -> 47200000
A29: DEPRECIACION | B29: =+B16 -> 0 | E29: DEPRECIACION | F29: =+B29 -> 0
A30: UTILIDAD OPERACIONAL | B30: =+B27-B28-B29 -> 0 | E30: UTILIDAD OPERACIONAL | F30: =+F27-F28-F29 -> 3.2754448e+08
B34: Punto de Equilibrio: Año 1
B38: Ajuste por inflacion | C38: 0.05
B39: Equilibrado+ | C39: 2025 | D39: =+C39+1 -> 2026 | E39: =+D39+1 -> 2027 | F39: =+E39+1 -> 2028 | G39: =+F39+1 -> 2029 | H39: =+G39+1 -> 2030
B40: % Participación | C40: 1 | D40: 1 | E40: 1 | F40: 1 | G40: 1 | H40: 1
B41: Costos Fijos | C41: =B28 -> 47200000 | D41: =C41*(1+$C$38) -> 49560000 | E41: =D41*(1+$C$38) -> 52038000 | F41: =E41*(1+$C$38) -> 54639900 | G41: =F41*(1+$C$38) -> 57371895 | H41: =G41*(1+$C$38) -> 60240490
B42: Depreciación y amortización | C42: =B29 -> 0 | D42: =C42*(1+$C$38) -> 0 | E42: =D42*(1+$C$38) -> 0 | F42: =E42*(1+$C$38) -> 0 | G42: =F42*(1+$C$38) -> 0 | H42: =G42*(1+$C$38) -> 0
B43: Costo Variable UNITARIO | C43: ='Identificación de costos'!E61 -> 1054340.5 | D43: =C43*(1+$C$38) -> 1107057.5 | E43: =D43*(1+$C$38) -> 1162410.4 | F43: =E43*(1+$C$38) -> 1220530.9 | G43: =F43*(1+$C$38) -> 1281557.4 | H43: =G43*(1+$C$38) -> 1345635.3
B44: Precio UNITARIO | C44: =B17 -> 1091814.9 | D44: =C44*(1+$C$38) -> 1146405.7 | E44: =D44*(1+$C$38) -> 1203726 | F44: =E44*(1+$C$38) -> 1263912.2 | G44: =F44*(1+$C$38) -> 1327107.9 | H44: =G44*(1+$C$38) -> 1393463.3
B45: Punto de Equilibrio | C45: =(C41+C42)/(C44-C43) -> 1259.5249 | D45: =(D41+D42)/(D44-D43) -> 1259.5249 | E45: =(E41+E42)/(E44-E43) -> 1259.5249 | F45: =(F41+F42)/(F44-F43) -> 1259.5249 | G45: =(G41+G42)/(G44-G43) -> 1259.5249 | H45: =(H41+H42)/(H44-H43) -> 1259.5249
B47: Cantidades Demandadas | C47: ='Estudio de Mercado-Encuesta'!C64 -> 1360800 | D47: ='Estudio de Mercado-Encuesta'!D64 -> 1374903 | E47: ='Estudio de Mercado-Encuesta'!E64 -> 1389722.4 | F47: ='Estudio de Mercado-Encuesta'!F64 -> 1404593.6 | G47: ='Estudio de Mercado-Encuesta'!G64 -> 1432123.7 | H47: ='Estudio de Mercado-Encuesta'!H64 -> 1432123.7

Sheet Plantilla Nomina
A2: ESTUDIO TÉCNICO
E4: EMPLEADOR | P4: EMPLEADO
E5: Seguridad social | H5: Parafiscales | K5: Prestaciones sociales
E6: 0.085 | F6: 0.12 | G6: 0.00522 | H6: =+'[2]SS-Para_PS'!D5 -> 0.02 | I6: =+'[2]SS-Para_PS'!D6 -> 0.03 | J6: =+'[2]SS-Para_PS'!D7 -> 0.04 | K6: =+'[2]SS-Para_PS'!D8 -> 0.083333333 | L6: =+'[2]SS-Para_PS'!D9 -> 0.01 | M6: =+'[2]SS-Para_PS'!D10 -> 0.083333333 | N6: =+'[2]SS-Para_PS'!D11 -> 0.041666667 | P6: 0.04 | Q6: 0.04 | R6: 0.01
A7: CARGO | C7: SALARIO | D7: AUXILIO TRANSPORTE | E7: APORTE SALUD | F7: APORTE PENSIÓN | G7: ARL | H7: SENA* | I7: ICBF* | J7: Caja Compensación Familiar | K7: Cesantías | L7: Intereses a las Cesantías | M7: Prima de Servicios | N7: Vacaciones | O7: Carga prestacional | P7: APORTE SALUD | Q7: APORTE PENSIÓN | R7: FONDO SOLIDARIDAD | S7: TOTAL DEDUCCIONES | T7: TOTAL DEVENGADO
A8: Jefe de tecnologia (CTO) | C8: 10000000 | E8: =+$C8*E$6 -> 850000 | F8: =+$C8*F$6 -> 1200000 | G8: =+$C8*G$6 -> 52200 | H8: =+$C8*H$6 -> 200000 | I8: =+$C8*I$6 -> 300000 | J8: =+$C8*J$6 -> 400000 | K8: =+($C8+D8)*K$6 -> 833333.33 | L8: =+($K8)*L$6 -> 8333.3333 | M8: =+($C8+D8)*M$6 -> 833333.33 | N8: =+$C8*N$6 -> 416666.67 | O8: =SUM(D8:N8) -> 5093866.7 | P8: =+$C8*P$6 -> 400000 | Q8: =+$C8*Q$6 -> 400000 | R8: =+$C8*R$6 -> 100000 | S8: =SUM(P8:R8) -> 900000 | T8: =+C8+D8-S8 -> 9100000 | U8: =+C8*12 -> 120000000 | V8: =+O8*12 -> 61126400
A9: Desarrollador Full-Stack | C9: 4500000 | E9: =+$C9*E$6 -> 382500 | F9: =+$C9*F$6 -> 540000 | G9: =+$C9*G$6 -> 23490 | H9: =+$C9*H$6 -> 90000 | I9: =+$C9*I$6 -> 135000 | J9: =+$C9*J$6 -> 180000 | K9: =+($C9+D9)*K$6 -> 375000 | L9: =+($K9)*L$6 -> 3750 | M9: =+($C9+D9)*M$6 -> 375000 | N9: =+$C9*N$6 -> 187500 | O9: =SUM(D9:N9) -> 2292240 | P9: =+$C9*P$6 -> 180000 | Q9: =+$C9*Q$6 -> 180000 | R9: =+$C9*R$6 -> 45000 | S9: =SUM(P9:R9) -> 405000 | T9: =+C9+D9-S9 -> 4095000 | U9: =+C9*12 -> 54000000 | V9: =+O9*12 -> 27506880
A10: Disenyador UX/UI | C10: 2400000 | D10: 200000 | E10: =+$C10*E$6 -> 204000 | F10: =+$C10*F$6 -> 288000 | G10: =+$C10*G$6 -> 12528 | H10: =+$C10*H$6 -> 48000 | I10: =+$C10*I$6 -> 72000 | J10: =+$C10*J$6 -> 96000 | K10: =+($C10+D10)*K$6 -> 216666.67 | L10: =+($K10)*L$6 -> 2166.6667 | M10: =+($C10+D10)*M$6 -> 216666.67 | N10: =+$C10*N$6 -> 100000 | O10: =SUM(D10:N10) -> 1456028 | P10: =+$C10*P$6 -> 96000 | Q10: =+$C10*Q$6 -> 96000 | R10: =+$C10*R$6 -> 24000 | S10: =SUM(P10:R10) -> 216000 | T10: =+C10+D10-S10 -> 2384000 | U10: =+C10*12 -> 28800000 | V10: =+O10*12 -> 17472336
A11: Soporte tecnico | C11: 2000000 | D11: 200000 | E11: =+$C11*E$6 -> 170000 | F11: =+$C11*F$6 -> 240000 | G11: =+$C11*G$6 -> 10440 | H11: =+$C11*H$6 -> 40000 | I11: =+$C11*I$6 -> 60000 | J11: =+$C11*J$6 -> 80000 | K11: =+($C11+D11)*K$6 -> 183333.33 | L11: =+($K11)*L$6 -> 1833.3333 | M11: =+($C11+D11)*M$6 -> 183333.33 | N11: =+$C11*N$6 -> 83333.333 | O11: =SUM(D11:N11) -> 1252273.3 | P11: =+$C11*P$6 -> 80000 | Q11: =+$C11*Q$6 -> 80000 | R11: =+$C11*R$6 -> 20000 | S11: =SUM(P11:R11) -> 180000 | T11: =+C11+D11-S11 -> 2020000 | U11: =+C11*12 -> 24000000 | V11: =+O11*12 -> 15027280
A12: Gerente General | C12: 4000000 | E12: =+$C12*E$6 -> 340000 | F12: =+$C12*F$6 -> 480000 | G12: =+$C12*G$6 -> 20880 | H12: =+$C12*H$6 -> 80000 | I12: =+$C12*I$6 -> 120000 | J12: =+$C12*J$6 -> 160000 | K12: =+($C12+D12)*K$6 -> 333333.33 | L12: =+($K12)*L$6 -> 3333.3333 | M12: =+($C12+D12)*M$6 -> 333333.33 | N12: =+$C12*N$6 -> 166666.67 | O12: =SUM(D12:N12) -> 2037546.7 | P12: =+$C12*P$6 -> 160000 | Q12: =+$C12*Q$6 -> 160000 | R12: =+$C12*R$6 -> 40000 | S12: =SUM(P12:R12) -> 360000 | T12: =+C12+D12-S12 -> 3640000 | U12: =+C12*12 -> 48000000 | V12: =+O12*12 -> 24450560
A13: Coordinador de Marketing | C13: 2500000 | D13: 200000 | E13: =+$C13*E$6 -> 212500 | F13: =+$C13*F$6 -> 300000 | G13: =+$C13*G$6 -> 13050 | H13: =+$C13*H$6 -> 50000 | I13: =+$C13*I$6 -> 75000 | J13: =+$C13*J$6 -> 100000 | K13: =+($C13+D13)*K$6 -> 225000 | L13: =+($K13)*L$6 -> 2250 | M13: =+($C13+D13)*M$6 -> 225000 | N13: =+$C13*N$6 -> 104166.67 | O13: =SUM(D13:N13) -> 1506966.7 | P13: =+$C13*P$6 -> 100000 | Q13: =+$C13*Q$6 -> 100000 | R13: =+$C13*R$6 -> 25000 | S13: =SUM(P13:R13) -> 225000 | T13: =+C13+D13-S13 -> 2475000 | U13: =+C13*12 -> 30000000 | V13: =+O13*12 -> 18083600
A14: Community Manager | C14: 1800000 | D14: 200000 | E14: =+$C14*E$6 -> 153000 | F14: =+$C14*F$6 -> 216000 | G14: =+$C14*G$6 -> 9396 | H14: =+$C14*H$6 -> 36000 | I14: =+$C14*I$6 -> 54000 | J14: =+$C14*J$6 -> 72000 | K14: =+($C14+D14)*K$6 -> 166666.67 | L14: =+($K14)*L$6 -> 1666.6667 | M14: =+($C14+D14)*M$6 -> 166666.67 | N14: =+$C14*N$6 -> 75000 | O14: =SUM(D14:N14) -> 1150396 | P14: =+$C14*P$6 -> 72000 | Q14: =+$C14*Q$6 -> 72000 | R14: =+$C14*R$6 -> 18000 | S14: =SUM(P14:R14) -> 162000 | T14: =+C14+D14-S14 -> 1838000
A15: Contador | C15: 2000000 | D15: 200000 | E15: =+$C15*E$6 -> 170000 | F15: =+$C15*F$6 -> 240000 | G15: =+$C15*G$6 -> 10440 | H15: =+$C15*H$6 -> 40000 | I15: =+$C15*I$6 -> 60000 | J15: =+$C15*J$6 -> 80000 | K15: =+($C15+D15)*K$6 -> 183333.33 | L15: =+($K15)*L$6 -> 1833.3333 | M15: =+($C15+D15)*M$6 -> 183333.33 | N15: =+$C15*N$6 -> 83333.333 | O15: =SUM(D15:N15) -> 1252273.3 | P15: =+$C15*P$6 -> 80000 | Q15: =+$C15*Q$6 -> 80000 | R15: =+$C15*R$6 -> 20000 | S15: =SUM(P15:R15) -> 180000 | T15: =+C15+D15-S15 -> 2020000
A16: Personal de Aseo Administrativo | C16: 1423500 | D16: 200000 | E16: =+$C16*E$6 -> 120997.5 | F16: =+$C16*F$6 -> 170820 | G16: =+$C16*G$6 -> 7430.67 | H16: =+$C16*H$6 -> 28470 | I16: =+$C16*I$6 -> 42705 | J16: =+$C16*J$6 -> 56940 | K16: =+($C16+D16)*K$6 -> 135291.67 | L16: =+($K16)*L$6 -> 1352.9167 | M16: =+($C16+D16)*M$6 -> 135291.67 | N16: =+$C16*N$6 -> 59312.5 | O16: =SUM(D16:N16) -> 958611.92 | P16: =+$C16*P$6 -> 56940 | Q16: =+$C16*Q$6 -> 56940 | R16: =+$C16*R$6 -> 14235 | S16: =SUM(P16:R16) -> 128115 | T16: =+C16+D16-S16 -> 1495385
A17: =+'[2]INFORMACIÓN GENERAL'!A15 -> 0
A18: TOTAL | C18: =SUM(C8:C16) -> 30623500 | D18: =+SUM(D8:D16) -> 1200000 | E18: =+SUM(E8:E16) -> 2602997.5 | F18: =+SUM(F8:F16) -> 3674820 | G18: =+SUM(G8:G16) -> 159854.67 | H18: =+SUM(H8:H16) -> 612470 | I18: =+SUM(I8:I16) -> 918705 | J18: =+SUM(J8:J16) -> 1224940 | K18: =+SUM(K8:K16) -> 2651958.3 | ... T18: =+SUM(T8:T16) -> 29067385
A21: SALARIOS | C21: =+C18 -> 30623500 | D21: =+C21-C12-C13 -> 24123500
A22: AUXILIO DE TRANSPORTE | C22: =+D18 -> 1200000
A23: CARGA PRESTACIONAL EMPRESA | C23: =SUM(E18:N18) -> 15800203 | D23: =+C23-O12-O13 -> 12255689
A24: TOTAL | C24: =SUM(C21:C23) -> 47623703 | D24: =SUM(D21:D23) -> 36379189 | E24: nomina administrativs
A25: ANUAL | C25: =+C24*12 -> 5.7148443e+08 | D25: =+D24*12 -> 4.3655027e+08 | E25: nomina anual

Sheet NominaIndividual 
G2: ESTUDIO TÉCNICO
G5: CALCULO DE NOMINA INDIVIDUAL
A6: IV | B6: Alto | C6: =1.74/100 -> 0.0174 | D6: =4.35/100 -> 0.0435 | E6: =6.96/100 -> 0.0696
A7: V | B7: Máximo | C7: =3.219/100 -> 0.03219 | D7: =6.96/100 -> 0.0696 | E7: =8.7/100 -> 0.087 | G7: EMPRESA | K7: EMPLEADO
G8: Calcule sus obligaciones con el trabajador y conozca cuánto le cuesta el empleado al proyecto | K8: Conozca el valor de las obligaciones de sus trabajadores y cuánto consignarles mensualmente.
B10: COMPAÑÍA | D10: EMPLEADO
B11: Porcentajes | D11: Porcentajes | G11: Salario laboral | J11: 1423500 | K11: Salario laboral | N11: =+J11 -> 1423500
K12: Auxilio de transporte | N12: 200000
B13: Básico | C13: intengral | D13: Básico | E13: intengral | G13: Carga prestacional | K13: Deducciones
G14: seguridad social | I14: =SUM(I15:I17) -> 0.21022 | J14: =SUM(J15:J17) -> 299248.17
B15: 0.085 | C15: 0.085 | D15: 0.04 | G15: Aporte en salud | I15: 0.085 | J15: =+$J$11*I15 -> 120997.5 | K15: Salud(EPS) | M15: 0.04 | N15: =+N11*M15 -> 56940
B16: 0.12 | C16: 0.12 | D16: 0.04 | E16: 0.04 | G16: Aporte en pensión | I16: 0.12 | J16: =+$J$11*I16 -> 170820 | K16: Pensiones | M16: 0.04 | N16: =+N11*M16 -> 56940
G17: ARL | I17: 0.00522 | J17: =+$J$11*I17 -> 7430.67
B18: 0.09 | C18: 0.09 | D18: 0.04 | E18: 0.04 | G18: Parafiscales | I18: =SUM(I19:I21) -> 0.09 | J18: =SUM(J19:J21) -> 128115 | K18: Fondo de solidaridad pensional
G19: Caja compensacin | I19: 0.04 | J19: =+$J$11*I19 -> 56940
G20: ICBF | I20: 0.03 | J20: =+$J$11*I20 -> 42705 | K20: TOTAL DEDUCCIONES | N20: =SUM(N15:O16) -> 113880
G21: SENA | I21: 0.02 | J21: =+$J$11*I21 -> 28470
G22: prestaciones sociales | I22: =SUM(I23:I26) -> 0.2183 | J22: =SUM(J23:J26) -> 331187.43
B23: 0.0833 | C23: 0.0833 | G23: Cesantias | I23: 0.0833 | J23: =($N$12+$J$11)*I23 -> 135237.55
B24: 0.12 | C24: 0.12 | G24: Intereses cesantias | I24: 0.01 | J24: =+$J$23*I24 -> 1352.3755 | K24: Retención en la Fuente "Estimado"
B25: 0.0833 | C25: 0.0833 | G25: Prima Legal | I25: 0.0833 | J25: =J23 -> 135237.55
B26: 0.0417 | C26: 0.0417 | G26: Vacaciones | I26: 0.0417 | J26: =+$J$11*I26 -> 59359.95
G29: COSTO MENSUAL CARGA PRESTACIONAL | J29: =+J22+J18+J14 -> 758550.6 | K29: TOTAL DEVENGADO EMPLEADO | N29: =+N11+N12-N20 -> 1509620
G30: SALARIO | J30: =+J11 -> 1423500
G31: AUXILIO DE TRANSPORTE COLABORADORES 2SMLV | J31: 200000
G33: VALOR TOTAL PAGADO EMPLEADOR | I33: =SUM(I15:I17,I19:I21,I23:I26) -> 0.51852 | J33: =SUM(J29:J31) -> 2382050.6 | K33: SALARIO MES JUNIO | N33: 3521700
G34: Dotación Legal (Opcional) | I34: 0.01 | J34: =$J$11*I34 -> 14235
G35: VALOR TOTAL PAGADO EMPLEADOR | I35: 0.03 | J35: =$J$11*I35 -> 42705 | K35: SALARIO ANUAL "Estimado"
G36: TOTAL CARGA PRESTACIONAL | I36: =SUM(I33:I35) -> 0.55852 | J36: =SUM(J33:J35) -> 2438990.6
B37: 69 | C37: =D37*$C$39 -> 141395000 | D37: 5000 | E37: 0.33 | G37: Por medio de los decretos 2360* y 2361** del 26 de Diciembre de 2019, el Gobierno Nacional estableció el salario mínimo y el auxilio de transporte para el año 2020. | P37: =+J29/N11 -> 0.53287713
B39: 1UVT | C39: 28279 | G39: De esta forma el salario mínimo que rige a partir del 1° de enero de 2020 es de $877.803 y el auxilio de transporte de $102.854.
C40: 0 | D40: 0.75
B41: UVT | C41: =ROUNDUP(N23/C39,0) -> 0
B43: SUBSISTENCIA | G43: FONDO DE SOLIDARIDAD PENSIONAL
B44: SMLV | C44: PESOS | D44: FACTOR
B45: 16 | C45: =B45*#REF! -> #REF! | D45: 0.2
B46: 17 | C46: =B46*#REF! -> #REF! | D46: 0.4
B47: 18 | C47: =B47*#REF! -> #REF! | D47: 0.6
B48: 19 | C48: =B48*#REF! -> #REF! | D48: 0.8
B49: 20 | C49: =B49*#REF! -> #REF! | D49: 1
B51: SOLIDARIDAD
B52: SMLV | C52: PESOS | D52: FACTOR
B53: 4 | C53: =B53*#REF! -> #REF! | D53: 0.01

Sheet Matriz Estudio Ambiental 
A3: ESTUDIO AMBIENTAL
A5: MATRIZ DE VALORACIÓN DE IMPACTOS AMBIENTALES
A6: ACTIVIDAD(ES) DEL PROYECTO (Tener presente el proceso realizado en el estudio técnico) | B6: ASPECTO AMBIENTAL Acciones que pueden causar el impacto ambiental | C6: TIPO IMPACTO AMBIENTAL Cambios en el medio ambiente | D6: COMPONENTE AMBIENTAL | N6: EFECTO IMPACTO AMBIENTAL
D7: Características físicas y químicas | F7: Condiciones biologicas | H7: Factores culturales | J7: Relaciones ecológicas | L7: Socioeconómico | N7: Efecto | O7: temporales | P7: Persistencia | Q7: Irreversibles | R7: Reversibilidad
D8: Tipo | E8: Variable | F8: Tipo | G8: Variable | H8: Tipo | I8: Variable | J8: Tipo | K8: Variable | L8: Tipo | M8: Variable
A16: EFECTO IMPACTO AMBIENTAL
A17: Temporales: se trata de un impacto a corto plazo y por tanto el medio puede recupera el estado anterior al impacto.
A18: Persistentes: se trata de un impacto a largo plazo con efectos duraderos en el tiempo y en el espacio. | B18: Cualquier cambio en el medio ambiente, ya sea adverso o beneficioso, como resultado total o parcial de los aspectos ambientales.
A19: Irreversibles: el impacto es de tal magnitud que genera un impacto permanente en el medio. | B19: Elemento o componente ambiental (suelo, agua, aire, flora y fauna) que interactúa con el aspecto ambiental generado por la entidad u organismo distrital y que puede presentar mejora o deterioro de acuerdo al impacto ambiental.
A20: Reversible: el medio natural podría recuperarse o no del todo a corto, medio o largo plazo.
A25: https://compartirejemplos.blogspot.com/2019/03/ejemplo-de-matriz-de-leopold-impacto.html

Sheet Guia-Matriz
B1: MATRIZ PARA LA EVALUACIÓN DE IMPACTOS AMBIENTALES (LEOPOLD)
A4: ASPECTO AMBIENTAL | B4: IMPACTO AMBIENTAL | C4: COMPONENTE AMBIENTAL
A5: A. Modificación del régimen | B5: a. Introducción de flora o fauna exóticas | C5: A. Características físicas y químicas | D5: 1. Tierra | E5: a. Recursos minerales
B6: b. Controles biológicos | E6: b. Materiales de construcción
B7: c. Modificación de hábitat | E7: c. Suelos
B8: d. Alteración de la cobertura vegetal del suelo | E8: d. Forma del terreno
B9: e. Alteración del flujo de agua subterránea | E9: e. Ondas electromagnéticas y radiación de fondo
B10: f. Alteración de patrones de drenaje | E10: f. Condiciones físicas únicas
B11: g. Control de ríos y modificación de flujo | D11: 2. Agua | E11: a. Superficial
B12: h. Canalización | E12: b. Oceáno
B13: i. Irrigación | E13: c. Subterránea
B14: j. Modificación del clima | E14: d. Calidad del agua
B15: k. Quema de bosques | E15: e. Temperatura
B16: l. Pavimentación | E16: f. Recarga
B17: m. Ruido y vibraciones | E17: g. Nieve, hielo y hielo perenne
A18: B. Transformación del terreno y construcción | B18: a. Urbanización | D18: 3. Atmósfera | E18: a. Calidad del aire (gases, partículas)
B19: b. Sitios y edificios industriales | E19: b. Clima (micro, macro)
B20: c. Aeropuertos | E20: c. Temperatura
B21: d. Carreteras y puentes | D21: 4. Procesos | E21: a. Avenidas
B22: e. Caminos y senderos | E22: b. Erosión
B23: f. Ferrocarriles | E23: c. Deposición (sedimentación, precipitación)
B24: g. Cables y ascensores | E24: d. Solución
B25: h. Líneas de transmisión, gasoductos y corredores | E25: e. Adsorción (intercambiop iónico)
B26: i. Barreras, incluyendo cercas | E26: f. Compactación y asentamiento
B27: j. Dragado y enderezamiento de canales | E27: g. Estabilidad de taludes (deslizamientos)
B28: k. Revestimiento de canales | E28: h. Esfuerzo-deformación (terremotos)
B29: l. Canales | E29: i. Movimientos de masas de aire
B30: m. Presas y embalses | C30: B. Condiciones biológicas | D30: 1. Flora | E30: a. Árboles
B31: n. Muelles, malecones, marinas, y terminales marítimos | E31: b. Arbustos
B32: o. Estructuras de altamar | E32: c. Pastos
B33: p. Estructuras de recreación | E33: d. Productos agrícolas
B34: q. Perforación y voladura | E34: e. Microflora
B35: r. Corte y relleno | E35: f. Plantas acuáticas
B36: s. Túneles y estructuras subterráneas | E36: h. Especies en peligro
A37: C. Explotación de recursos | B37: a. Perforación y voladura | E37: h. Barreras
B38: b. Excavación de superficie | E38: i. Corredores
B39: c. Excavación del subsuelo | D39: 2. Fauna | E39: a. Pájaros
B40: d. Perforación de pozos | E40: b. Animales terrestres, incluyendo reptiles
B41: e. Dragado | E41: c. Peces y moluscos
B42: f. Tala de bosques | E42: d. Organismos bénticos
B43: g. Pesca comercial y caza | E43: e. Insectos
A44: D. Procesamiento | B44: a. Agricultura | E44: f. Microfauna
B45: b. Ganadería y pastoreo | E45: g. Especies en peligro
B46: c. Plantas de engorde de ganado | E46: h. Barreras
B47: d. Plantas de producción de leche | E47: i. Corredores
B48: e. Generación de energía | C48: C. Factores culturales | D48: 1. Uso de la tierra | E48: a. Vida silvestre y espacios abiertos
B49: f. Procesamiento de minerales | E49: b. Humedales
B50: g. Industria metalúrgica | E50: c. Bosques
B51: h. Industria química | E51: d. Pastoreo
B52: i. Industria textil | E52: e. Agricultura
B53: j. Automóviles y aeronaves | E53: f. Residencial
B54: k. Refinación de petróleo | E54: g. Comercial
B55: l. Alimentos | E55: h. Industrial
B56: m. Madera | E56: i. Minería y extracción de materiales
B57: n. Pulpa y papel | D57: 2. Recreación | E57: a. Caza
B58: o. Almacenamiento de productos | E58: b. Pesca
A59: E. Modificación del terreno | B59: a. Control de erosión y terrazas | E59: c. Navegación por placer
B60: b. Sellado de minas y control de desechos | E60: d. Natación
B61: c. Rehabilitación de minas a tajo abierto | E61: e. Camping y caminatas
B62: d. Paisajismo | E62: f. Salidas al campo
B63: e. Dragado de puertos | E63: g. Centros de vacaciones y placer
B64: f. Drenaje de humedales y pantanos | D64: 3. Interés estético y humano | E64: a. Vistas escénicas
A65: F. Renovación de recursos | B65: a. Reforestación | E65: b. Calidad de vida silvestre
B66: b. Gestión de vida silvestre | E66: c. Calidad de espacio abierto
B67: c. Recarga de agua subterránea | E67: d. Diseño del paisaje
B68: d. Aplicación de fertilizantes | E68: e. Condiciones físicas únicas
B69: e. Reciclaje de residuos | E69: f. Parques y reservas forestales
A70: G. Cambios en el tráfico | B70: a. Red ferroviaria | E70: g. Monumentos
B71: b. Automóviles | E71: h. Especies o ecosistemas raros y únicos
B72: c. Camiones | E72: i. Sitios y objetos históricos o arqueológicos
B73: d. Transporte de carga | E73: j. Presencia de elementos raros
B74: e. Aviones | D74: 4. Aspectos culturales | E74: a. Patrones culturales (estilo de vida)
B75: f. Ríos y canales | E75: b. Salud y seguridad
B76: g. Botes de placer | E76: c. Empleo
B77: h. Senderos | E77: d. Densidad de población
B78: i. Cables y ascensores | D78: 5. Facilidades y actividades humanas | E78: a. Estructuras
B79: j. Comunicación | E79: b. Red de transporte
B80: k. Tuberías y conductos forzados | E80: c. Redes de servicios
A81: H. Emplazamiento y tratamiento de residuos | B81: a. Vertido en los océanos | E81: d. Manejo de residuos
B82: b. Rellenos sanitarios | E82: e. Barreras
B83: c. Colocación de residuos mineros | E83: f. Corredores
B84: d. Almacenamiento debajo del terreno | C84: D. Relaciones ecológicas | E84: a. Salinización de recursos hídricos
B85: e. Eliminación de basura | E85: b. Eutroficación
B86: f. Inundación de pozos de petróleo | E86: c. Insectos vectores de enfermedades
B87: g. Colocación de pozos de petróleo | E87: d. Cadenas tróficas
B88: h. Agua de enfriamiento industrial | E88: e. Salinización del terreno
B89: i. Aguas servidas municipales, incluyendo irrigación | E89: f. Aumento del área arbustiva
B90: j. Descarga de efluentes municipales | E90: g. Otros
B91: k. Lagunas de estabilización y oxidación | C91: E. Otros | E91: a. A ser determinado
B92: l. Tanques sépticos, comerciales y domésticos | E92: b. A ser determinado
B93: m. Emisiones de chimeneas al aire libre
B94: n. Lubricantes usados
A95: I. Tratamientos químicos | B95: a. Fertilización
B96: b. Deshielo de carreteras
B97: c. Estabilización de suelos
B98: d. Control de malezas
B99: e. Control de insectos con pesticidas
A100: J. Accidentes | B100: a. Explosiones
B101: b. Vertidos y filtraciones
B102: c. Falla operacional

Sheet Estudio Legal
A2: ESTUDIO LEGAL
A4: Fase de constitución
B5: Cantidad | C5: costo
A6: Certificado de Homonimia | B6: 1 | C6: 11600
A7: Escritura Pública/ minuta/acta de inicio | B7: 1 | C7: 2000000
A8: Inscribirse en cámara de comercio | B8: 1 | C8: 8100
A9: Apertura de cuenta bancaria - Bancolombia | B9: 1 | C9: 36000
A10: RUT y/o NIT (DIAN) | B10: 1 | C10: 0
A11: Registro Mercantil | B11: 1 | C11: 69000
A12: Pago impuestos de Rentas departamentales
A13: VALOR TOTAL | C13: =SUM(C6:C12) -> 2124700
A16: Fase de operación
B17: Cantidad | C17: costo
A18: Registros de libros contables | B18: 1 | C18: 23100
A19: Licencia de Bomberos | C19: 0
A20: Avisos y tableros | B20: 1 | C20: 50000
A21: Licencia Ambiental | C21: 0
A22: Licencia de Funcionamiento | C22: 0
A23: Permiso de Uso del Suelo (planeación municipal) | C23: 0
A24: Registro INVIMA | B24: 1 | C24: 1500000
A25: Permiso ICA | C25: 0
A26: Sayco y Acimpo | B26: 1 | C26: 1600000
A27: VALOR TOTAL | C27: =SUM(C26:C26) -> 1600000

Sheet Evaluación Financiera 
B2: EVALUACION FINANCIERA DEL PROYECTO
B6: Flujos de Caja de la Operación
C7: 0 | D7: 1 | E7: 2 | F7: 3 | G7: 4 | H7: 5
B8: % incremento en servicios | E8: =5%+1% -> 0.06 | F8: =E8+1% -> 0.07 | G8: =F8+1% -> 0.08 | H8: =G8+1% -> 0.09
B9: % incremento en costos (inflación + 3 puntos) | C9: 0.0551 | D9: =C9*(1+3%) -> 0.056753 | E9: =D9*(1+3%) -> 0.05845559 | F9: =E9*(1+3%) -> 0.060209258 | G9: =F9*(1+3%) -> 0.062015535 | H9: =G9*(1+3%) -> 0.063876001
B10: % incremento en precio (inflación)
B11: Tasa de impuestos | D11: 0.3 | E11: 0.3 | F11: 0.3 | G11: 0.3 | H11: 0.3
B13: Serivicios adquiridos | D13: 500 | E13: =D13*(1+E8) -> 530 | F13: =E13*(1+F8) -> 567.1 | G13: =F13*(1+G8) -> 612.468 | H13: =G13*(1+H8) -> 667.59012
B15: Precio del servicio | C15: ='Identificación de costos'!D88 -> 1091814.9 | D15: =C15*(1+$C$9) -> 1151973.9 | E15: =D15*(1+$C$9) -> 1215447.7 | F15: =E15*(1+$C$9) -> 1282418.9 | G15: =F15*(1+$C$9) -> 1353080.1 | H15: =G15*(1+$C$9) -> 1427634.8
B16: costos variables | D16: 30000 | E16: =D16*($C$9+1) -> 31653 | F16: =E16*($C$9+1) -> 33397.08 | G16: =F16*($C$9+1) -> 35237.259 | H16: =G16*($C$9+1) -> 37178.832
C18: Periodos
C19: 0 | D19: 1 | E19: 2 | F19: 3 | G19: 4 | H19: 5
B20: Ingresos por venta de producto o prestación de servicio | D20: =+D13*D15 -> 5.7598696e+08 | E20: =+E13*E15 -> 6.4418727e+08 | F20: =+F13*F15 -> 7.2725973e+08 | G20: =+G13*G15 -> 8.2871828e+08 | H20: =+H13*H15 -> 9.5307492e+08
B21: INGRESOS TOTALES | D21: =SUM(D20) -> 5.7598696e+08 | E21: =SUM(E20) -> 6.4418727e+08 | F21: =SUM(F20) -> 7.2725973e+08 | G21: =SUM(G20) -> 8.2871828e+08 | H21: =SUM(H20) -> 9.5307492e+08 | I21: 0
B22: Costo Fijo TOTAL | D22: ='Identificación de costos'!G27 -> 343404736 | E22: =D22*(1+$C$9) -> 3.6232634e+08 | F22: =E22*(1+$C$9) -> 3.8229052e+08 | G22: =F22*(1+$C$9) -> 4.0335473e+08 | H22: =G22*(1+$C$9) -> 4.2557957e+08
B23: Gastos nomina administrativa | D23: ='Identificación de costos'!G37 -> 2.2355154e+08 | E23: =D23*($C$9+1) -> 2.3586922e+08 | F23: =E23*($C$9+1) -> 2.4886562e+08 | G23: =F23*($C$9+1) -> 2.6257811e+08 | H23: =G23*($C$9+1) -> 2.7704617e+08
B24: Costo Variable | D24: =D16 -> 30000 | E24: =E16 -> 31653 | F24: =F16 -> 33397.08 | G24: =G16 -> 35237.259 | H24: =H16 -> 37178.832
B25: COSTOS VARIABLES TOTALES | D25: =SUM(D24:D24) -> 30000 | E25: =SUM(E24:E24) -> 31653 | F25: =SUM(F24:F24) -> 33397.08 | G25: =SUM(G24:G24) -> 35237.259 | H25: =SUM(H24:H24) -> 37178.832 | I25: 0
B26: Depreciación y Amortización TOTAL (costos contables)
B27: COSTO OPERACIONALES TOTAL = Costo Fijo TOTAL + Costo Variable TOTAL + Depreciación + Amortización | D27: =+D22+D23+D25+D26 -> 5.6698627e+08 | E27: =+E22+E23+E25+E26 -> 5.9822721e+08 | F27: =+F22+F23+F25+F26 -> 6.3118953e+08 | G27: =+G22+G23+G25+G26 -> 6.6596808e+08 | H27: =+H22+H23+H25+H26 -> 7.0266292e+08
B28: UTILIDAD OPERATIVA = Ingresos - Costos | D28: =+D21-D27 -> 9000690.7 | E28: =+E21-E27 -> 45960059 | F28: =+F21-F27 -> 96070198 | G28: =+G21-G27 -> 1.6275021e+08 | H28: =+H21-H27 -> 2.50412e+08 | I28: 0
B29: Impuesto Operativo = Utilidad Operativa * T, T: Tasa de Impuestos | D29: =D28*$D$11 -> 2700207.2 | E29: =E28*$D$11 -> 13788018 | F29: =F28*$D$11 -> 28821059 | G29: =G28*$D$11 -> 48825062 | H29: =H28*$D$11 -> 75123600
B30: UODI = Utilidad Operativa DESPUES de Impuestos = Utilidad Operativa - Impuesto Operativo | D30: =+D28-D29 -> 6300483.5 | E30: =+E28-E29 -> 32172042 | F30: =+F28-F29 -> 67249139 | G30: =+G28-G29 -> 1.1392514e+08 | H30: =+H28-H29 -> 1.752884e+08
B31: (+) Costos contables: Depreciación y Amortización Activos Intangibles TOTAL | D31: ='C. inversiones y costos ctables'!F18 -> 6820000 | E31: ='C. inversiones y costos ctables'!G18 -> 6820000 | F31: ='C. inversiones y costos ctables'!H18 -> 6820000 | G31: ='C. inversiones y costos ctables'!I18 -> 6820000 | H31: ='C. inversiones y costos ctables'!J18 -> 6820000
B32: FLUJO DE CAJA OPERATIVO = UODI + Depreciación + Amortización | D32: =+D30-D31 -> -519516.54 | E32: =+E30-E31 -> 25352042 | F32: =+F30-F31 -> 60429139 | G32: =+G30-G31 -> 1.0710514e+08 | H32: =+H30-H31 -> 1.684684e+08
B34: Datos para el Flujos de Caja de la Inversión
B36: Calendario de Inversión
B38: Activos Fijos | C38: 0 | D38: 1 | E38: 2 | F38: 3 | G38: 4 | I38: 5
B39: Software (licencias básicas: CRM, contabilidad, diseño) | C39: 3000000
B40: Dispositivos de prueba (celulares/tabletas para testeo) | C40: 2400000
B41: Computadores de desarrollo (ingenieros, diseño, IA) | C41: 9000000
B42: Laptops administrativas / comerciales | C42: 4000000
B43: Escritorios operativos | C43: 4500000
B44: Sillas ergonómicas | C44: 2500000
B45: Router y red local | C45: 1200000
B46: Pantallas para monitoreo de alertas | C46: 3000000
B47: Tablets para validación con usuarios / EPS | C47: 8000000
B48: Inversión en Activos FIJOS | C48: =SUM(C39:C47) -> 37600000 | D48: 0 | E48: 0 | F48: 0 | G48: 0 | I48: 0
B50: VALOR DE DESECHO DE LOS ACTIVOS FIJOS
B51: Activos | C51: Precio TOTAL Activo | D51: Depreciación Acumulada | E51: Valor Libros = Precio Activo - Depreciación Acumulada | F51: Valor Comercial | G51: Pérdida o Ganancia por venta de activos = Valor comercial - Valor Libros | H51: Impuesto T de año 5 | I51: Valor de Desecho = Valor comercial - Impuesto = Valor Libros
B52: Software (licencias básicas: CRM, contabilidad, diseño) | C52: =C39 -> 3000000 | D52: ='C. inversiones y costos ctables'!K9 -> 3000000 | E52: =C52-D52 -> 0
B53: Dispositivos de prueba (celulares/tabletas para testeo) | C53: =C40 -> 2400000 | D53: ='C. inversiones y costos ctables'!K10 -> 2400000 | E53: =C53-D53 -> 0
B54: Computadores de desarrollo (ingenieros, diseño, IA) | C54: =C41 -> 9000000 | D54: ='C. inversiones y costos ctables'!K11 -> 9000000 | E54: =C54-D54 -> 0
B55: Laptops administrativas / comerciales | C55: =C42 -> 4000000 | D55: ='C. inversiones y costos ctables'!K12 -> 4000000 | E55: =C55-D55 -> 0
B56: Escritorios operativos | C56: =C43 -> 4500000 | D56: ='C. inversiones y costos ctables'!K13 -> 2250000 | E56: =C56-D56 -> 2250000 | F56: =E56 -> 2250000 | G56: 0 | H56: 0 | I56: =F56 -> 2250000
B57: Sillas ergonómicas | C57: =C44 -> 2500000 | D57: ='C. inversiones y costos ctables'!K14 -> 1250000 | E57: =C57-D57 -> 1250000 | F57: =E57 -> 1250000 | G57: 0 | H57: 0 | I57: =F57 -> 1250000
B58: Router y red local | C58: =C45 -> 1200000 | D58: ='C. inversiones y costos ctables'!K15 -> 1200000 | E58: =C58-D58 -> 0
B59: Pantallas para monitoreo de alertas | C59: =C46 -> 3000000 | D59: ='C. inversiones y costos ctables'!K16 -> 3000000 | E59: =C59-D59 -> 0
B60: Tablets para validación con usuarios / EPS | C60: =C47 -> 8000000 | D60: ='C. inversiones y costos ctables'!K17 -> 8000000 | E60: =C60-D60 -> 0
B63: Periodo de desfase | C63: 90 | D63: 90 | E63: 90 | F63: 90 | G63: 90 | H63: 90
B64: Días año | C64: 360 | D64: 360 | E64: 360 | F64: 360 | G64: 360 | H64: 360
B66: Inversión en Capital de Trabajo (ΔKT)
C67: 0 | D67: 1 | E67: 2 | F67: 3 | G67: 4 | H67: 5
B68: Costos TOTALES (Sin depreciación y amortización) | D68: =D27 -> 5.6698627e+08 | E68: =E27 -> 5.9822721e+08 | F68: =F27 -> 6.3118953e+08 | G68: =G27 -> 6.6596808e+08 | H68: =H27 -> 7.0266292e+08
B69: Capital de Trabajo (KT) | D69: =(D68*D63)/D64 -> 1.4174657e+08 | E69: =(E68*E63)/E64 -> 1.495568e+08 | F69: =(F68*F63)/F64 -> 1.5779738e+08 | G69: =(G68*G63)/G64 -> 1.6649202e+08 | H69: =(H68*H63)/H64 -> 1.7566573e+08
B70: Inversión en Capital de Trabajo (ΔKT) | C70: =D69 -> 1.4174657e+08 | D70: =E69-D69 -> 7810235.9 | E70: =F69-E69 -> 8240579.9 | F70: =G69-F69 -> 8694635.8 | G70: =H69-G69 -> 9173710.3 | H70: =I69-H69 -> -1.7566573e+08
B73: Flujo de Caja de la Inversión
B75: Año | C75: 0 | D75: 1 | E75: 2 | F75: 3 | G75: 4 | I75: 5
B76: Inversión en Activos Fijos (IAF) | C76: =C48 -> 37600000
B77: Valor de desecho de Activos Fijos (Flujo de caja de la venta de activos) | H77: ='C. inversiones y costos ctables'!L18 -> 3500000
B78: Valor de procedimientos legales | C78: ='Estudio Legal'!C13+'Estudio Legal'!C27 -> 3724700
B79: Inversión en Activos Intangibles (IAI) | C79: 25000000
B80: Inversión en Capital de Trabajo (IKT) | C80: =C70 -> 1.4174657e+08 | D80: =D70 -> 7810235.9 | E80: =E70 -> 8240579.9 | F80: =F70 -> 8694635.8 | G80: =G70 -> 9173710.3 | H80: =H70 -> -1.7566573e+08
B81: FLUJO DE CAJA INVERSIÓN | C81: =-(C76+C79+C80+C78) -> -2.0807127e+08 | D81: =-(D76+D79+D80) -> -7810235.9 | E81: =-(E76+E79+E80) -> -8240579.9 | F81: =-(F76+F79+F80) -> -8694635.8 | G81: =-(G76+G79+G80) -> -9173710.3 | H81: =-(H76+H79+H80+H77) -> 1.7216573e+08
B85: Flujo de Caja del Proyecto: Flujos de caja que genera el proyecto independientemente de la financiación
C87: 0 | D87: 1 | E87: 2 | F87: 3 | G87: 4 | H87: 5
B88: Flujo de Caja de OPERACIÓN | C88: =C32 -> 0 | D88: =D32 -> -519516.54 | E88: =E32 -> 25352042 | F88: =F32 -> 60429139 | G88: =G32 -> 1.0710514e+08 | H88: =H32 -> 1.684684e+08
B89: Flujo de Caja de INVERSIÓN | C89: =C81 -> -2.0807127e+08 | D89: =D81 -> -7810235.9 | E89: =E81 -> -8240579.9 | F89: =F81 -> -8694635.8 | G89: =G81 -> -9173710.3 | H89: =H81 -> 1.7216573e+08
B90: FLUJO DE CAJA DEL PROYECTO = FLUJO DE CAJA LIBRE | C90: =C88+C89 -> -2.0807127e+08 | D90: =D88+D89 -> -8329752.4 | E90: =E88+E89 -> 17111462 | F90: =F88+F89 -> 51734503 | G90: =G88+G89 -> 97931434 | H90: =H88+H89 -> 3.4063413e+08
B93: Flujos de Caja de la Financiación
B95: Inverision total
B96: Entidad Financiera
B97: Recursos propios
C100: DEUDA 1
B101: Monto Préstamo | C101: =C70*0.5 -> 70873284
B102: Kd = Tasa de Interés (Anual) | C102: 0.19 | D102: BBVBA para PYMES
B103: Plazo (Años) | C103: 5
B104: Cuota FIJA | C104: =PMT(C102,C103,C101) -> -23179119
B105: Tasa de Impuestos | C105: 0.3 | D105: =+C105 -> 0.3 | E105: =+D105 -> 0.3 | F105: =+E105 -> 0.3 | G105: =+F105 -> 0.3 | H105: =+G105 -> 0.3
C107: DEUDA 1
C108: 0 | D108: 1 | E108: 2 | F108: 3 | G108: 4 | H108: 5
B109: Saldo (saldo anterior- abono a capital) | C109: =C101 -> 70873284 | D109: =C109-D110 -> 61160089 | E109: =D109-E110 -> 49601386 | F109: =E109-F110 -> 35846530 | G109: =F109-G110 -> 19478252 | H109: =G109-H110 -> 0
B110: Amortización de Capital = cuota-interes | D110: =-D112-D111 -> 9713195.4 | E110: =-E112-E111 -> 11558702 | F110: =-F112-F111 -> 13754856 | G110: =-G112-G111 -> 16368279 | H110: =-H112-H111 -> 19478252
B111: Interés = Saldo del periodo anterior * tasa de interés | D111: =C109*$C$102 -> 13465924 | E111: =D109*$C$102 -> 11620417 | F111: =E109*$C$102 -> 9424263.3 | G111: =F109*$C$102 -> 6810840.7 | H111: =G109*$C$102 -> 3700867.8
B112: Cuota | D112: =$C$104 -> -23179119 | E112: =$C$104 -> -23179119 | F112: =$C$104 -> -23179119 | G112: =$C$104 -> -23179119 | H112: =$C$104 -> -23179119
B113: Beneficio Tributario (Intereses*Tasa impuesto) | D113: =D111*D105 -> 4039777.2 | E113: =E111*E105 -> 3486125 | F113: =F111*F105 -> 2827279 | G113: =G111*G105 -> 2043252.2 | H113: =H111*H105 -> 1110260.3 | K113: =SUM(D113:I113) -> 13506694
B114: FLUJO DE CAJA FINANCIACIÓN | D114: =D112+D113 -> -19139342 | E114: =E112+E113 -> -19692994 | F114: =F112+F113 -> -20351840 | G114: =G112+G113 -> -21135867 | H114: =H112+H113 -> -22068859
B117: Flujo de Caja del Inversionista: Flujo de caja que reciben los dueños del negocio
C119: 0 | D119: 1 | E119: 2 | F119: 3 | G119: 4 | H119: 5
B120: Flujo de Caja de PROYECTO | C120: =C90 -> -2.0807127e+08 | D120: =D90 -> -8329752.4 | E120: =E90 -> 17111462 | F120: =F90 -> 51734503 | G120: =G90 -> 97931434 | H120: =H90 -> 3.4063413e+08
B121: Flujo de Caja de FINANCIACIÓN | C121: =C109 -> 70873284 | D121: =D114 -> -19139342 | E121: =E114 -> -19692994 | F121: =F114 -> -20351840 | G121: =G114 -> -21135867 | H121: =H114 -> -22068859
B122: FLUJO DE CAJA DEL INVERSIONISTA | C122: =C120+C121 -> -1.3719798e+08 | D122: =D120+D121 -> -27469095 | E122: =E120+E121 -> -2581532.6 | F122: =F120+F121 -> 31382663 | G122: =G120+G121 -> 76795566 | H122: =H120+H121 -> 3.1856527e+08
B125: CRITERIOS DE SELECCIÓN DEL PROYECTO
B127: Costo Promedio Ponderado de Capital (WACC)
B129: Fuente | C129: Monto | D129: Participaciones = Monto Fuente / Inversión inicial | E129: Costo de la Fuente | F129: Participación * Costo de la Fuente | G129: =+F130*35% -> 0.022651246
B130: Deuda (Monto de deuda) | C130: =C121 -> 70873284 | D130: =C130/C132 -> 0.34062023 | E130: =C102 -> 0.19 | F130: =D130*E130 -> 0.064717844
B131: Aporte de accionistas (Flujo de Caja de Inversionista, año 0) | C131: =-C90-C109 -> 1.3719798e+08 | D131: =C131/C132 -> 0.65937977 | E131: =C140 -> 0.6075 | F131: =E131*D131 -> 0.40057321
B132: Inversión Inicial (I0) | C132: =SUM(C130:C131) -> 2.0807127e+08 | F132: =SUM(F130:F131) -> 0.46529105
A135: Modelo Capm: permite calcular la tasa de retorno de un activo financiero en función del riesgo asumido.
A136: CAPM (Ke = Rf + (Em - Rf)*B)
...
